Workbook

Sheet Summary
A1: 美博工程服務有限公司
A2: MS_Q1241_24_kp (MTR C9644-24C Extension of Fitness Room at KBD Recreation & Sports Centre)
A4: (Project No. MS_Q1241_24)
A5: 地盤糧期狀況
A6: 工期 | B6: 12/2024 - 01/2026 | C6: (390天)
A8: 總承建商(MC): | B8: Mepork Engineering Service Limited
A9: 承包商(SUB-CON):
A10: 承包商(SUB-CON):
A13: 承建金額: | B13: 7400000
A14: (a) | C14: Option 1
A15: (b) | C15: Option 2
A16: (c)
A17: (d)
A18: (A) Sub-total: | B18: =SUM(B13:B17) -> 7400000
A21: 承包商(SUB-CON): | B21: 宏發工程公司
A22: (a) | B22: ='Project Summary'!J13 -> 1900000 | C22: Builder's Works | D22: 宏發建築工程公司 | E22: SC-003
A23: (b) | B23: ='Project Summary'!J11 -> 800000 | C23: FS | D23: 大同工程有限公司 | E23: SC-002
A24: (c) | B24: ='Project Summary'!J26+'Project Summary'!J27 -> 1212880 | C24: EL Labour | D24: 照明工程有限公司 | E24: SC-010 & SC-010.1
A25: (d) | B25: ='Project Summary'!J16 -> 800000 | C25: ECS | D25: 盈泊工程公司 | E25: SC-004
A26: (e) | B26: ='Project Summary'!J23+'Project Summary'!J24 -> 15500 | C26: Design of Hoarding, SE | D26: 華文工程有限公司 | E26: SC-008 & SC-008.1
A27: (f)
A30: (B) Sub-total: | B30: =SUM(B22:B29) -> 4728380
A32: (C) = (A) - (B) 利潤: | B32: =B18-B30 -> 2671620
A33: Less Expenses : | B33: ='Project Summary'!J9 -> 44360 | C33: Insurance - EC | D33: 恒傑保險業務有限公司 | E33: O-001
A34: Less Expenses : | B34: ='Project Summary'!J14 -> 15000 | C34: Q167/21 搭架比EMSD驗收燈柱 | D34: 宏發建築工程公司 | E34: SC-003A
A35: Less Expenses : | B35: ='Project Summary'!J17 -> 83000 | C35: 代買冷氣機 | D35: 盈泊工程公司 | E35: SC-004A
A36: Less Expenses : | B36: ='Project Summary'!J18 -> 27242.5 | C36: Levies | D36: 環境保護署 | E36: O-005
A37: Less Expenses : | B37: ='Project Summary'!J19+'Project Summary'!J21 -> 284000 | C37: Safety | D37: 滅火筒安全顧問 | E37: O-006 & O-006.1
A38: Less Expenses : | B38: ='Project Summary'!J22 -> 2000 | C38: CP Training | D38: MTR | E38: O-007
A39: Less Expenses : | B39: ='Project Summary'!J59 -> 14006 | C39: Levies | D39: 建造業議會 | E39: O-012
A40: Less Expenses : | B40: ='Project Summary'!J60 -> 12038.9 | C40: Miscellaneous | E40: O-013
A41: Less Expenses : | B41: ='Project Summary'!J61 -> 6279 | C41: Levies | D41: 肺塵埃沉着病補償基金委員會 | E41: O-014
A42: Less Expenses : | B42: ='Project Summary'!J25 -> 1640 | C42: Body Check | D42: 聯康醫療 | E42: O-009
A43: Less Expenses : | B43: ='Project Summary'!J62 -> 174600 | C43: Light fitting | D43: ALCO LIGHTING (H.K.) LTD | E43: M-015
A44: Less Expenses : | B44: =SUM('Project Summary'!J28:J46) -> 187121.1 | C44: EL - Material | D44: 信成電器材料有限公司 | E44: M-011.1 - M-011.19
A45: Less Expenses :
A46: Less Expenses :
A47: Less Expenses :
A48: Less Expenses :
A49: Less Expenses :
A50: Less Expenses : | E50: Remark:
A51: (D) Total Sum of Profit (TBC): | B51: =B32-SUM(B33:B50) -> 1820332.5 | E51: 12000 | F51: 扣宏發
E52: 1500 | F52: CP 扣判頭
A53: (E) 預計利潤: | B53: =B18*10.6% -> 784400 | C53: (10.6% Profit)
A54: (F) = (E) - (D) 其他項目支出: | B54: =B51-B53 -> 1035932.5
A56: Mepork Engineering Services Limited | H56: 承包商(SUB-CON)
A57: 糧款期數 | B57: 申請糧款日期 | C57: 申請工程金額 HK$ | D57: 申請工程金額 百分比 | E57: 收入 （則師批款) HK$ | F57: 則師批款 百分比 | G57: 則師批數日期 | H57: 支出 （美博批款) HK$ | I57: 則師批款 百分比 | J57: 美博批數日期
A58: Interim Payment No. | B58: Applied Date | C58: Payment Application | D58: % | E58: Payment Certified Amount | F58: % | G58: Payment Certificate Date | H58: Payment Certified Amount | I58: % | J58: Payment Certificate Date
A59: IP-01 | B59: 45703 | C59: 286605 | D59: =SUM($C$59:C59)/$B$18 -> 0.038730405 | E59: 182481.3 | F59: =SUM($E$59:E59)/$B$18 -> 0.024659635 | G59: 45726 | I59: =SUM($H$59:H59)/$B$30 -> 0
A60: IP-02 | B60: 45733 | C60: 177763.05 | D60: =SUM($C$59:C60)/$B$18 -> 0.062752439 | E60: 99373.5 | F60: =SUM($E$59:E60)/$B$18 -> 0.038088486 | G60: 45756 | I60: =SUM($H$59:H60)/$B$30 -> 0
A61: IP-03 | B61: 45783 | C61: 278784.23 | D61: =SUM($C$59:C61)/$B$18 -> 0.10042598 | E61: 249814.8 | F61: =SUM($E$59:E61)/$B$18 -> 0.071847243 | G61: 45806 | I61: =SUM($H$59:H61)/$B$30 -> 0
A62: IP-04 | B62: 45786 | C62: 268119.45 | D62: =SUM($C$59:C62)/$B$18 -> 0.13665834 | E62: 178865.1 | F62: =SUM($E$59:E62)/$B$18 -> 0.096018203 | G62: 45842 | I62: =SUM($H$59:H62)/$B$30 -> 0
A63: IP-05 | B63: 45859 | C63: 848025.45 | D63: =SUM($C$59:C63)/$B$18 -> 0.25125638 | E63: 557768.7 | F63: =SUM($E$59:E63)/$B$18 -> 0.17139235 | G63: 45881 | I63: =SUM($H$59:H63)/$B$30 -> 0
A64: IP-06 | B64: 45889 | C64: 841890.15 | D64: =SUM($C$59:C64)/$B$18 -> 0.36502531 | E64: 350842.5 | F64: =SUM($E$59:E64)/$B$18 -> 0.2188035 | G64: 45911 | I64: =SUM($H$59:H64)/$B$30 -> 0
A65: IP-07 | B65: 45923 | C65: 987280.43 | D65: =SUM($C$59:C65)/$B$18 -> 0.49844159 | E65: 431916.3 | F65: =SUM($E$59:E65)/$B$18 -> 0.27717057 | G65: 45946 | I65: =SUM($H$59:H65)/$B$30 -> 0
A66: IP-08 | B66: 45952 | C66: 1190913.5 | D66: =SUM($C$59:C66)/$B$18 -> 0.65937585 | E66: 591593.4 | F66: =SUM($E$59:E66)/$B$18 -> 0.35711562 | G66: 45979 | I66: =SUM($H$59:H66)/$B$30 -> 0
A67: IP-09 | B67: 46000 | C67: 2139244.9 | D67: =SUM($C$59:C67)/$B$18 -> 0.948463 | E67: 1543503.4 | F67: =SUM($E$59:E67)/$B$18 -> 0.56569716 | G67: 46023 | I67: =SUM($H$59:H67)/$B$30 -> 0
A68: IP-10 | B68: 46028 | C68: 1434253.2 | D68: =SUM($C$59:C68)/$B$18 -> 1.142281 | E68: 562026 | F68: =SUM($E$59:E68)/$B$18 -> 0.64164662 | G68: 46050 | I68: =SUM($H$59:H68)/$B$30 -> 0
E69: =SUM(E59:E68) -> 4748185 | H69: =SUM(H59:H68) -> 0
D71: 總收入: | E71: =E69 -> 4748185 | H71: =E69-H69 -> 4748185
A72: Prepared By: | B72: Katie Puk | D72: 總支出: | E72: =-'代支工程, 物料'!K153 -> -5395140.2
A73: Updated on: | B73: =NOW() -> 46178.604 | D73: 墊支: | E73: =SUM(E71:E72) -> -646955.25

Sheet 代支工程, 物料
A1: =Summary!A2 -> MS_Q1241_24_kp (MTR C9644-24C Extension of Fitness Room at KBD Recreation & Sports Centre)
A2: 代支工程總表
A3: Updated on 12/12/2024
A4: No. | B4: Link | C4: Invoice Date | D4: Invoice No. | E4: Quotation No. | F4: Sub-contractors' No | G4: Company Name | H4: Company Name (in Chinese) | I4: Description | J4: Contract Amount (HK$) | K4: Paid Amount (HK$) | L4: Remainder Amount (HK$) | M4: OA日期 | N4: OA編號 | O4: MC IP-No. | P4: B/C to sub-contractor | Q4: Sub-IP No. | R4: Reamrk
A5: 1 | B5: =HYPERLINK("Z:\MePork\000 綜合\020 報價合約\Quotation\2024\MS_Q1241_24_kp (C9644-24C Extension of Fitness Room at KBD Recreation & Sports Centre)\P1 - Payment\Payment records\"&A5&".PDF",A5) -> 1 | C5: 45637 | D5: I0482530 | F5: O-001 | G5: =IFERROR(VLOOKUP($F5,'Project Summary'!$B$9:$M$106,3,FALSE),"") -> REALIFE INSURANCE BROKERS LTD. | H5: =IFERROR(VLOOKUP($F5,'Project Summary'!$B$9:$M$106,4,FALSE),"") -> 恒傑保險業務有限公司 | I5: =IFERROR(VLOOKUP($F5,'Project Summary'!$B$9:$M$106,5,FALSE),"") -> Insurance - EC | J5: =IFERROR(VLOOKUP($F5,'Project Summary'!$B$9:$M$106,7,FALSE),"") -> 44360 | K5: 44360 | L5: =IFERROR(J5-K5,"") -> 0 | R5: Pokfulam No. 599 Transfer to WCH No.1 | S5: =HYPERLINK("Q:\Project No. 016A - HKSR PHI Renovation at Pokfulam\P1 - Payment\Payment Records\"&A5&".PDF",A5)
A6: 2 | B6: =HYPERLINK("Z:\MePork\000 綜合\020 報價合約\Quotation\2024\MS_Q1241_24_kp (C9644-24C Extension of Fitness Room at KBD Recreation & Sports Centre)\P1 - Payment\Payment records\"&A6&".PDF",A6) -> 2 | C6: 45645 | D6: Q-CEL-FS-2411-01 | F6: SC-002 | G6: =IFERROR(VLOOKUP($F6,'Project Summary'!$B$9:$M$106,3,FALSE),"") -> CHASE ENGINEERING LIMITED | H6: =IFERROR(VLOOKUP($F6,'Project Summary'!$B$9:$M$106,4,FALSE),"") -> 大同工程有限公司 | I6: =IFERROR(VLOOKUP($F6,'Project Summary'!$B$9:$M$106,5,FALSE),"") -> Fire Services Installation | J6: =IFERROR(VLOOKUP($F6,'Project Summary'!$B$9:$M$106,7,FALSE),"") -> 800000 | K6: 100000 | L6: =IFERROR(J6-K6,"") -> 700000
A7: 3 | B7: =HYPERLINK("Z:\MePork\000 綜合\020 報價合約\Quotation\2024\MS_Q1241_24_kp (C9644-24C Extension of Fitness Room at KBD Recreation & Sports Centre)\P1 - Payment\Payment records\"&A7&".PDF",A7) -> 3 | C7: 45646 | F7: SC-003 | G7: =IFERROR(VLOOKUP($F7,'Project Summary'!$B$9:$M$106,3,FALSE),"") -> WANG FAT CONSTRUCTION CO. | H7: =IFERROR(VLOOKUP($F7,'Project Summary'!$B$9:$M$106,4,FALSE),"") -> 宏發建築工程公司 | I7: =IFERROR(VLOOKUP($F7,'Project Summary'!$B$9:$M$106,5,FALSE),"") -> Builder's Works | J7: =IFERROR(VLOOKUP($F7,'Project Summary'!$B$9:$M$106,7,FALSE),"") -> 1900000 | K7: 200000 | L7: =IFERROR(J7-K7,"") -> 1700000
A8: 4 | B8: =HYPERLINK("Z:\MePork\000 綜合\020 報價合約\Quotation\2024\MS_Q1241_24_kp (C9644-24C Extension of Fitness Room at KBD Recreation & Sports Centre)\P1 - Payment\Payment records\"&A8&".PDF",A8) -> 4 | C8: 45642 | D8: 12024180 | F8: SC-004 | G8: =IFERROR(VLOOKUP($F8,'Project Summary'!$B$9:$M$106,3,FALSE),"") -> YING PAK ENGINEERING COMPANY | H8: =IFERROR(VLOOKUP($F8,'Project Summary'!$B$9:$M$106,4,FALSE),"") -> 盈泊工程公司 | I8: MVAC Installation - IP-01 | J8: =IFERROR(VLOOKUP($F8,'Project Summary'!$B$9:$M$106,7,FALSE),"") -> 800000 | K8: 150000 | L8: =IFERROR(J8-K8,"") -> 650000
A9: 5 | B9: =HYPERLINK("Z:\MePork\000 綜合\020 報價合約\Quotation\2024\MS_Q1241_24_kp (C9644-24C Extension of Fitness Room at KBD Recreation & Sports Centre)\P1 - Payment\Payment records\"&A9&".PDF",A9) -> 5 | C9: 45657 | D9: 705330010 | F9: O-005 | G9: =IFERROR(VLOOKUP($F9,'Project Summary'!$B$9:$M$106,3,FALSE),"") -> Environmental Protection Department | H9: =IFERROR(VLOOKUP($F9,'Project Summary'!$B$9:$M$106,4,FALSE),"") -> 環境保護署 | I9: =IFERROR(VLOOKUP($F9,'Project Summary'!$B$9:$M$106,5,FALSE),"") -> Waste Dispoal | J9: =IFERROR(VLOOKUP($F9,'Project Summary'!$B$9:$M$106,7,FALSE),"") -> 27242.5 | K9: 15000 | L9: =IFERROR(J9-K9,"") -> 12242.5
A10: 6 | B10: =HYPERLINK("Z:\MePork\000 綜合\020 報價合約\Quotation\2024\MS_Q1241_24_kp (C9644-24C Extension of Fitness Room at KBD Recreation & Sports Centre)\P1 - Payment\Payment records\"&A10&".PDF",A10) -> 6 | C10: 45659 | D10: INV2/1/2025 | F10: O-006 | G10: =IFERROR(VLOOKUP($F10,'Project Summary'!$B$9:$M$106,3,FALSE),"") -> FIRE EXTINGUISHER SAFETY CONSULTANT | H10: =IFERROR(VLOOKUP($F10,'Project Summary'!$B$9:$M$106,4,FALSE),"") -> 滅火筒安全顧問 | I10: =IFERROR(VLOOKUP($F10,'Project Summary'!$B$9:$M$106,5,FALSE),"") -> Safety | J10: =IFERROR(VLOOKUP($F10,'Project Summary'!$B$9:$M$106,7,FALSE),"") -> 272000 | K10: 7742 | L10: =IFERROR(J10-K10,"") -> 264258
A11: 7 | B11: =HYPERLINK("Z:\MePork\000 綜合\020 報價合約\Quotation\2024\MS_Q1241_24_kp (C9644-24C Extension of Fitness Room at KBD Recreation & Sports Centre)\P1 - Payment\Payment records\"&A11&".PDF",A11) -> 7 | C11: 25/1/2025 | F11: SC-003 | G11: =IFERROR(VLOOKUP($F11,'Project Summary'!$B$9:$M$106,3,FALSE),"") -> WANG FAT CONSTRUCTION CO. | H11: =IFERROR(VLOOKUP($F11,'Project Summary'!$B$9:$M$106,4,FALSE),"") -> 宏發建築工程公司 | I11: =IFERROR(VLOOKUP($F11,'Project Summary'!$B$9:$M$106,5,FALSE),"") -> Builder's Works | J11: =IFERROR(VLOOKUP($F11,'Project Summary'!$B$9:$M$106,7,FALSE),"") -> 1900000 | K11: 180000 | L11: =IFERROR(J11-K11,"") -> 1720000
A12: 8 | B12: =HYPERLINK("Z:\MePork\000 綜合\020 報價合約\Quotation\2024\MS_Q1241_24_kp (C9644-24C Extension of Fitness Room at KBD Recreation & Sports Centre)\P1 - Payment\Payment records\"&A12&".PDF",A12) -> 8 | C12: 45690 | D12: 102-004363-001 | F12: O-007 | G12: =IFERROR(VLOOKUP($F12,'Project Summary'!$B$9:$M$106,3,FALSE),"") -> MTR | H12: =IFERROR(VLOOKUP($F12,'Project Summary'!$B$9:$M$106,4,FALSE),"") -> 0 | I12: =IFERROR(VLOOKUP($F12,'Project Summary'!$B$9:$M$106,5,FALSE),"") -> CP Training | J12: =IFERROR(VLOOKUP($F12,'Project Summary'!$B$9:$M$106,7,FALSE),"") -> 2000 | K12: 500 | L12: =IFERROR(J12-K12,"") -> 1500
A13: 9 | B13: =HYPERLINK("Z:\MePork\000 綜合\020 報價合約\Quotation\2024\MS_Q1241_24_kp (C9644-24C Extension of Fitness Room at KBD Recreation & Sports Centre)\P1 - Payment\Payment records\"&A13&".PDF",A13) -> 9 | C13: 45701 | D13: INV13/2/2025 | F13: O-006 | G13: =IFERROR(VLOOKUP($F13,'Project Summary'!$B$9:$M$106,3,FALSE),"") -> FIRE EXTINGUISHER SAFETY CONSULTANT | H13: =IFERROR(VLOOKUP($F13,'Project Summary'!$B$9:$M$106,4,FALSE),"") -> 滅火筒安全顧問 | I13: =IFERROR(VLOOKUP($F13,'Project Summary'!$B$9:$M$106,5,FALSE),"") -> Safety | J13: =IFERROR(VLOOKUP($F13,'Project Summary'!$B$9:$M$106,7,FALSE),"") -> 272000 | K13: 16000 | L13: =IFERROR(J13-K13,"") -> 256000
A14: 10 | B14: =HYPERLINK("Z:\MePork\000 綜合\020 報價合約\Quotation\2024\MS_Q1241_24_kp (C9644-24C Extension of Fitness Room at KBD Recreation & Sports Centre)\P1 - Payment\Payment records\"&A14&".PDF",A14) -> 10 | C14: 45716 | F14: O-007 | G14: =IFERROR(VLOOKUP($F14,'Project Summary'!$B$9:$M$106,3,FALSE),"") -> MTR | H14: =IFERROR(VLOOKUP($F14,'Project Summary'!$B$9:$M$106,4,FALSE),"") -> 0 | I14: =IFERROR(VLOOKUP($F14,'Project Summary'!$B$9:$M$106,5,FALSE),"") -> CP Training | J14: =IFERROR(VLOOKUP($F14,'Project Summary'!$B$9:$M$106,7,FALSE),"") -> 2000 | K14: 1000 | L14: =IFERROR(J14-K14,"") -> 1000
A15: 11 | B15: =HYPERLINK("Z:\MePork\000 綜合\020 報價合約\Quotation\2024\MS_Q1241_24_kp (C9644-24C Extension of Fitness Room at KBD Recreation & Sports Centre)\P1 - Payment\Payment records\"&A15&".PDF",A15) -> 11 | C15: 45726 | D15: INV10/3/2025 | F15: O-006 | G15: =IFERROR(VLOOKUP($F15,'Project Summary'!$B$9:$M$106,3,FALSE),"") -> FIRE EXTINGUISHER SAFETY CONSULTANT | H15: =IFERROR(VLOOKUP($F15,'Project Summary'!$B$9:$M$106,4,FALSE),"") -> 滅火筒安全顧問 | I15: =IFERROR(VLOOKUP($F15,'Project Summary'!$B$9:$M$106,5,FALSE),"") -> Safety | J15: =IFERROR(VLOOKUP($F15,'Project Summary'!$B$9:$M$106,7,FALSE),"") -> 272000 | K15: 16000 | L15: =IFERROR(J15-K15,"") -> 256000
A16: 12 | B16: =HYPERLINK("Z:\MePork\000 綜合\020 報價合約\Quotation\2024\MS_Q1241_24_kp (C9644-24C Extension of Fitness Room at KBD Recreation & Sports Centre)\P1 - Payment\Payment records\"&A16&".PDF",A16) -> 12 | C16: 45735 | D16: DN18553-QL | F16: O-009 | G16: =IFERROR(VLOOKUP($F16,'Project Summary'!$B$9:$M$106,3,FALSE),"") -> UCMG | H16: =IFERROR(VLOOKUP($F16,'Project Summary'!$B$9:$M$106,4,FALSE),"") -> 聯康醫療 | I16: =IFERROR(VLOOKUP($F16,'Project Summary'!$B$9:$M$106,5,FALSE),"") -> Body Check | J16: =IFERROR(VLOOKUP($F16,'Project Summary'!$B$9:$M$106,7,FALSE),"") -> 1640 | K16: 540 | L16: =IFERROR(J16-K16,"") -> 1100
A17: 13 | B17: =HYPERLINK("Z:\MePork\000 綜合\020 報價合約\Quotation\2024\MS_Q1241_24_kp (C9644-24C Extension of Fitness Room at KBD Recreation & Sports Centre)\P1 - Payment\Payment records\"&A17&".PDF",A17) -> 13 | C17: 45748 | D17: INV 1/4/2025 | F17: O-006 | G17: =IFERROR(VLOOKUP($F17,'Project Summary'!$B$9:$M$106,3,FALSE),"") -> FIRE EXTINGUISHER SAFETY CONSULTANT | H17: =IFERROR(VLOOKUP($F17,'Project Summary'!$B$9:$M$106,4,FALSE),"") -> 滅火筒安全顧問 | I17: =IFERROR(VLOOKUP($F17,'Project Summary'!$B$9:$M$106,5,FALSE),"") -> Safety | J17: =IFERROR(VLOOKUP($F17,'Project Summary'!$B$9:$M$106,7,FALSE),"") -> 272000 | K17: 16000 | L17: =IFERROR(J17-K17,"") -> 256000
A18: 14 | B18: =HYPERLINK("Z:\MePork\000 綜合\020 報價合約\Quotation\2024\MS_Q1241_24_kp (C9644-24C Extension of Fitness Room at KBD Recreation & Sports Centre)\P1 - Payment\Payment records\"&A18&".PDF",A18) -> 14 | C18: 45763 | D18: DN18593-QL | F18: O-009 | G18: =IFERROR(VLOOKUP($F18,'Project Summary'!$B$9:$M$106,3,FALSE),"") -> UCMG | H18: =IFERROR(VLOOKUP($F18,'Project Summary'!$B$9:$M$106,4,FALSE),"") -> 聯康醫療 | I18: =IFERROR(VLOOKUP($F18,'Project Summary'!$B$9:$M$106,5,FALSE),"") -> Body Check | J18: =IFERROR(VLOOKUP($F18,'Project Summary'!$B$9:$M$106,7,FALSE),"") -> 1640 | K18: 270 | L18: =IFERROR(J18-K18,"") -> 1370
A19: 15 | B19: =HYPERLINK("Z:\MePork\000 綜合\020 報價合約\Quotation\2024\MS_Q1241_24_kp (C9644-24C Extension of Fitness Room at KBD Recreation & Sports Centre)\P1 - Payment\Payment records\"&A19&".PDF",A19) -> 15 | C19: 45749 | D19: INV 2/4/2025 | F19: O-006.1 | G19: =IFERROR(VLOOKUP($F19,'Project Summary'!$B$9:$M$106,3,FALSE),"") -> FIRE EXTINGUISHER SAFETY CONSULTANT | H19: =IFERROR(VLOOKUP($F19,'Project Summary'!$B$9:$M$106,4,FALSE),"") -> 滅火筒安全顧問 | I19: =IFERROR(VLOOKUP($F19,'Project Summary'!$B$9:$M$106,5,FALSE),"") -> Safety Review | J19: =IFERROR(VLOOKUP($F19,'Project Summary'!$B$9:$M$106,7,FALSE),"") -> 12000 | K19: 12000 | L19: =IFERROR(J19-K19,"") -> 0
A20: 16 | B20: =HYPERLINK("Z:\MePork\000 綜合\020 報價合約\Quotation\2024\MS_Q1241_24_kp (C9644-24C Extension of Fitness Room at KBD Recreation & Sports Centre)\P1 - Payment\Payment records\"&A20&".PDF",A20) -> 16 | C20: 45785 | D20: P24-28 | F20: SC-010 | G20: =IFERROR(VLOOKUP($F20,'Project Summary'!$B$9:$M$106,3,FALSE),"") -> CHIU MING COMPANY LIMITED | H20: =IFERROR(VLOOKUP($F20,'Project Summary'!$B$9:$M$106,4,FALSE),"") -> 照明工程有限公司 | I20: EL - IP-01 | J20: =IFERROR(VLOOKUP($F20,'Project Summary'!$B$9:$M$106,7,FALSE),"") -> 1100000 | K20: 126628 | L20: =IFERROR(J20-K20,"") -> 973372
A21: 17 | B21: =HYPERLINK("Z:\MePork\000 綜合\020 報價合約\Quotation\2024\MS_Q1241_24_kp (C9644-24C Extension of Fitness Room at KBD Recreation & Sports Centre)\P1 - Payment\Payment records\"&A21&".PDF",A21) -> 17 | C21: 45720 | D21: MB-202402b | F21: SC-008 | G21: =IFERROR(VLOOKUP($F21,'Project Summary'!$B$9:$M$106,3,FALSE),"") -> WAH MAN ENGINEERING COMPANY | H21: =IFERROR(VLOOKUP($F21,'Project Summary'!$B$9:$M$106,4,FALSE),"") -> 華文工程有限公司 | I21: =IFERROR(VLOOKUP($F21,'Project Summary'!$B$9:$M$106,5,FALSE),"") -> Design of Hoarding | J21: =IFERROR(VLOOKUP($F21,'Project Summary'!$B$9:$M$106,7,FALSE),"") -> 9500 | K21: 9500 | L21: =IFERROR(J21-K21,"") -> 0
A22: 18 | B22: =HYPERLINK("Z:\MePork\000 綜合\020 報價合約\Quotation\2024\MS_Q1241_24_kp (C9644-24C Extension of Fitness Room at KBD Recreation & Sports Centre)\P1 - Payment\Payment records\"&A22&".PDF",A22) -> 18 | C22: 45792 | D22: INV 15/5/2025 | F22: O-006 | G22: =IFERROR(VLOOKUP($F22,'Project Summary'!$B$9:$M$106,3,FALSE),"") -> FIRE EXTINGUISHER SAFETY CONSULTANT | H22: =IFERROR(VLOOKUP($F22,'Project Summary'!$B$9:$M$106,4,FALSE),"") -> 滅火筒安全顧問 | I22: =IFERROR(VLOOKUP($F22,'Project Summary'!$B$9:$M$106,5,FALSE),"") -> Safety | J22: =IFERROR(VLOOKUP($F22,'Project Summary'!$B$9:$M$106,7,FALSE),"") -> 272000 | K22: 16000 | L22: =IFERROR(J22-K22,"") -> 256000
A23: 19 | B23: =HYPERLINK("Z:\MePork\000 綜合\020 報價合約\Quotation\2024\MS_Q1241_24_kp (C9644-24C Extension of Fitness Room at KBD Recreation & Sports Centre)\P1 - Payment\Payment records\"&A23&".PDF",A23) -> 19 | C23: 45791 | F23: O-007 | G23: =IFERROR(VLOOKUP($F23,'Project Summary'!$B$9:$M$106,3,FALSE),"") -> MTR | H23: =IFERROR(VLOOKUP($F23,'Project Summary'!$B$9:$M$106,4,FALSE),"") -> 0 | I23: =IFERROR(VLOOKUP($F23,'Project Summary'!$B$9:$M$106,5,FALSE),"") -> CP Training | J23: =IFERROR(VLOOKUP($F23,'Project Summary'!$B$9:$M$106,7,FALSE),"") -> 2000 | K23: 500 | L23: =IFERROR(J23-K23,"") -> 1500
A24: 20 | B24: =HYPERLINK("Z:\MePork\000 綜合\020 報價合約\Quotation\2024\MS_Q1241_24_kp (C9644-24C Extension of Fitness Room at KBD Recreation & Sports Centre)\P1 - Payment\Payment records\"&A24&".PDF",A24) -> 20 | C24: 45818 | D24: DN3347788 | F24: O-012 | G24: =IFERROR(VLOOKUP($F24,'Project Summary'!$B$9:$M$106,3,FALSE),"") -> CONSTRUCTION INDUSTRY COUNCIL | H24: =IFERROR(VLOOKUP($F24,'Project Summary'!$B$9:$M$106,4,FALSE),"") -> 建造業議會 | I24: =IFERROR(VLOOKUP($F24,'Project Summary'!$B$9:$M$106,5,FALSE),"") -> Levies | J24: =IFERROR(VLOOKUP($F24,'Project Summary'!$B$9:$M$106,7,FALSE),"") -> 14006 | K24: 1493 | L24: =IFERROR(J24-K24,"") -> 12513
A25: 21 | B25: =HYPERLINK("Z:\MePork\000 綜合\020 報價合約\Quotation\2024\MS_Q1241_24_kp (C9644-24C Extension of Fitness Room at KBD Recreation & Sports Centre)\P1 - Payment\Payment records\"&A25&".PDF",A25) -> 21 | C25: 45835 | F25: SC-003 | G25: =IFERROR(VLOOKUP($F25,'Project Summary'!$B$9:$M$106,3,FALSE),"") -> WANG FAT CONSTRUCTION CO. | H25: =IFERROR(VLOOKUP($F25,'Project Summary'!$B$9:$M$106,4,FALSE),"") -> 宏發建築工程公司 | I25: =IFERROR(VLOOKUP($F25,'Project Summary'!$B$9:$M$106,5,FALSE),"") -> Builder's Works | J25: =IFERROR(VLOOKUP($F25,'Project Summary'!$B$9:$M$106,7,FALSE),"") -> 1900000 | K25: 190000 | L25: =IFERROR(J25-K25,"") -> 1710000
A26: 22 | B26: =HYPERLINK("Z:\MePork\000 綜合\020 報價合約\Quotation\2024\MS_Q1241_24_kp (C9644-24C Extension of Fitness Room at KBD Recreation & Sports Centre)\P1 - Payment\Payment records\"&A26&".PDF",A26) -> 22 | C26: 45835 | F26: SC-002 | G26: =IFERROR(VLOOKUP($F26,'Project Summary'!$B$9:$M$106,3,FALSE),"") -> CHASE ENGINEERING LIMITED | H26: =IFERROR(VLOOKUP($F26,'Project Summary'!$B$9:$M$106,4,FALSE),"") -> 大同工程有限公司 | I26: =IFERROR(VLOOKUP($F26,'Project Summary'!$B$9:$M$106,5,FALSE),"") -> Fire Services Installation | J26: =IFERROR(VLOOKUP($F26,'Project Summary'!$B$9:$M$106,7,FALSE),"") -> 800000 | K26: 235000 | L26: =IFERROR(J26-K26,"") -> 565000
A27: 23 | B27: =HYPERLINK("Z:\MePork\000 綜合\020 報價合約\Quotation\2024\MS_Q1241_24_kp (C9644-24C Extension of Fitness Room at KBD Recreation & Sports Centre)\P1 - Payment\Payment records\"&A27&".PDF",A27) -> 23 | C27: 45821 | D27: INV3//2025 | F27: O-006 | G27: =IFERROR(VLOOKUP($F27,'Project Summary'!$B$9:$M$106,3,FALSE),"") -> FIRE EXTINGUISHER SAFETY CONSULTANT | H27: =IFERROR(VLOOKUP($F27,'Project Summary'!$B$9:$M$106,4,FALSE),"") -> 滅火筒安全顧問 | I27: =IFERROR(VLOOKUP($F27,'Project Summary'!$B$9:$M$106,5,FALSE),"") -> Safety | J27: =IFERROR(VLOOKUP($F27,'Project Summary'!$B$9:$M$106,7,FALSE),"") -> 272000 | K27: 16000 | L27: =IFERROR(J27-K27,"") -> 256000
A28: 24 | B28: =HYPERLINK("Z:\MePork\000 綜合\020 報價合約\Quotation\2024\MS_Q1241_24_kp (C9644-24C Extension of Fitness Room at KBD Recreation & Sports Centre)\P1 - Payment\Payment records\"&A28&".PDF",A28) -> 24 | C28: 45809 | D28: P24-28 | F28: SC-010 | G28: =IFERROR(VLOOKUP($F28,'Project Summary'!$B$9:$M$106,3,FALSE),"") -> CHIU MING COMPANY LIMITED | H28: =IFERROR(VLOOKUP($F28,'Project Summary'!$B$9:$M$106,4,FALSE),"") -> 照明工程有限公司 | I28: EL - IP-02 | J28: =IFERROR(VLOOKUP($F28,'Project Summary'!$B$9:$M$106,7,FALSE),"") -> 1100000 | K28: 108500 | L28: =IFERROR(J28-K28,"") -> 991500
A29: 25 | B29: =HYPERLINK("Z:\MePork\000 綜合\020 報價合約\Quotation\2024\MS_Q1241_24_kp (C9644-24C Extension of Fitness Room at KBD Recreation & Sports Centre)\P1 - Payment\Payment records\"&A29&".PDF",A29) -> 25 | F29: O-013 | G29: =IFERROR(VLOOKUP($F29,'Project Summary'!$B$9:$M$106,3,FALSE),"") -> Miscellaneous | H29: =IFERROR(VLOOKUP($F29,'Project Summary'!$B$9:$M$106,4,FALSE),"") -> 0 | I29: =IFERROR(VLOOKUP($F29,'Project Summary'!$B$9:$M$106,5,FALSE),"") -> 0 | J29: =IFERROR(VLOOKUP($F29,'Project Summary'!$B$9:$M$106,7,FALSE),"") -> 12038.9 | K29: 1920 | L29: =IFERROR(J29-K29,"") -> 10118.9
A30: 26 | B30: =HYPERLINK("Z:\MePork\000 綜合\020 報價合約\Quotation\2024\MS_Q1241_24_kp (C9644-24C Extension of Fitness Room at KBD Recreation & Sports Centre)\P1 - Payment\Payment records\"&A30&".PDF",A30) -> 26 | C30: 45832 | D30: DN3581600 | F30: O-014 | G30: =IFERROR(VLOOKUP($F30,'Project Summary'!$B$9:$M$106,3,FALSE),"") -> PNEUMOCONIOSIS COMPENSATION FUND BOARD | H30: =IFERROR(VLOOKUP($F30,'Project Summary'!$B$9:$M$106,4,FALSE),"") -> 肺塵埃沉着病補償基金委員會 | I30: =IFERROR(VLOOKUP($F30,'Project Summary'!$B$9:$M$106,5,FALSE),"") -> Levies | J30: =IFERROR(VLOOKUP($F30,'Project Summary'!$B$9:$M$106,7,FALSE),"") -> 6279 | K30: 422 | L30: =IFERROR(J30-K30,"") -> 5857
A31: 27 | B31: =HYPERLINK("Z:\MePork\000 綜合\020 報價合約\Quotation\2024\MS_Q1241_24_kp (C9644-24C Extension of Fitness Room at KBD Recreation & Sports Centre)\P1 - Payment\Payment records\"&A31&".PDF",A31) -> 27 | C31: 45825 | D31: DN18711-QL | F31: O-009 | G31: =IFERROR(VLOOKUP($F31,'Project Summary'!$B$9:$M$106,3,FALSE),"") -> UCMG | H31: =IFERROR(VLOOKUP($F31,'Project Summary'!$B$9:$M$106,4,FALSE),"") -> 聯康醫療 | I31: =IFERROR(VLOOKUP($F31,'Project Summary'!$B$9:$M$106,5,FALSE),"") -> Body Check | J31: =IFERROR(VLOOKUP($F31,'Project Summary'!$B$9:$M$106,7,FALSE),"") -> 1640 | K31: 280 | L31: =IFERROR(J31-K31,"") -> 1360
A32: 28 | B32: =HYPERLINK("Z:\MePork\000 綜合\020 報價合約\Quotation\2024\MS_Q1241_24_kp (C9644-24C Extension of Fitness Room at KBD Recreation & Sports Centre)\P1 - Payment\Payment records\"&A32&".PDF",A32) -> 28 | C32: 45757 | D32: 64440 | F32: M-011.1 | G32: =IFERROR(VLOOKUP($F32,'Project Summary'!$B$9:$M$106,3,FALSE),"") -> SHUN SHING ELECTRICALS CO. LTD | H32: =IFERROR(VLOOKUP($F32,'Project Summary'!$B$9:$M$106,4,FALSE),"") -> 信成電器材料有限公司 | I32: =IFERROR(VLOOKUP($F32,'Project Summary'!$B$9:$M$106,5,FALSE),"") -> EL - Material | J32: =IFERROR(VLOOKUP($F32,'Project Summary'!$B$9:$M$106,7,FALSE),"") -> 32940 | K32: 32940 | L32: =IFERROR(J32-K32,"") -> 0
A33: 29 | B33: =HYPERLINK("Z:\MePork\000 綜合\020 報價合約\Quotation\2024\MS_Q1241_24_kp (C9644-24C Extension of Fitness Room at KBD Recreation & Sports Centre)\P1 - Payment\Payment records\"&A33&".PDF",A33) -> 29 | C33: 45753 | D33: 64331 | F33: M-011.2 | G33: =IFERROR(VLOOKUP($F33,'Project Summary'!$B$9:$M$106,3,FALSE),"") -> SHUN SHING ELECTRICALS CO. LTD | H33: =IFERROR(VLOOKUP($F33,'Project Summary'!$B$9:$M$106,4,FALSE),"") -> 信成電器材料有限公司 | I33: =IFERROR(VLOOKUP($F33,'Project Summary'!$B$9:$M$106,5,FALSE),"") -> EL - Material | J33: =IFERROR(VLOOKUP($F33,'Project Summary'!$B$9:$M$106,7,FALSE),"") -> 39055 | K33: 39055 | L33: =IFERROR(J33-K33,"") -> 0
A34: 30 | B34: =HYPERLINK("Z:\MePork\000 綜合\020 報價合約\Quotation\2024\MS_Q1241_24_kp (C9644-24C Extension of Fitness Room at KBD Recreation & Sports Centre)\P1 - Payment\Payment records\"&A34&".PDF",A34) -> 30 | C34: 45752 | D34: 64187 | F34: M-011.3 | G34: =IFERROR(VLOOKUP($F34,'Project Summary'!$B$9:$M$106,3,FALSE),"") -> SHUN SHING ELECTRICALS CO. LTD | H34: =IFERROR(VLOOKUP($F34,'Project Summary'!$B$9:$M$106,4,FALSE),"") -> 信成電器材料有限公司 | I34: =IFERROR(VLOOKUP($F34,'Project Summary'!$B$9:$M$106,5,FALSE),"") -> EL - Material | J34: =IFERROR(VLOOKUP($F34,'Project Summary'!$B$9:$M$106,7,FALSE),"") -> 21960 | K34: 21960 | L34: =IFERROR(J34-K34,"") -> 0
A35: 31 | B35: =HYPERLINK("Z:\MePork\000 綜合\020 報價合約\Quotation\2024\MS_Q1241_24_kp (C9644-24C Extension of Fitness Room at KBD Recreation & Sports Centre)\P1 - Payment\Payment records\"&A35&".PDF",A35) -> 31 | C35: 45775 | D35: 64286 | F35: M-011.4 | G35: =IFERROR(VLOOKUP($F35,'Project Summary'!$B$9:$M$106,3,FALSE),"") -> SHUN SHING ELECTRICALS CO. LTD | H35: =IFERROR(VLOOKUP($F35,'Project Summary'!$B$9:$M$106,4,FALSE),"") -> 信成電器材料有限公司 | I35: =IFERROR(VLOOKUP($F35,'Project Summary'!$B$9:$M$106,5,FALSE),"") -> EL - Material | J35: =IFERROR(VLOOKUP($F35,'Project Summary'!$B$9:$M$106,7,FALSE),"") -> 19740 | K35: 19740 | L35: =IFERROR(J35-K35,"") -> 0
A36: 32 | B36: =HYPERLINK("Z:\MePork\000 綜合\020 報價合約\Quotation\2024\MS_Q1241_24_kp (C9644-24C Extension of Fitness Room at KBD Recreation & Sports Centre)\P1 - Payment\Payment records\"&A36&".PDF",A36) -> 32 | C36: 45773 | D36: 64272 | F36: M-011.5 | G36: =IFERROR(VLOOKUP($F36,'Project Summary'!$B$9:$M$106,3,FALSE),"") -> SHUN SHING ELECTRICALS CO. LTD | H36: =IFERROR(VLOOKUP($F36,'Project Summary'!$B$9:$M$106,4,FALSE),"") -> 信成電器材料有限公司 | I36: =IFERROR(VLOOKUP($F36,'Project Summary'!$B$9:$M$106,5,FALSE),"") -> EL - Material | J36: =IFERROR(VLOOKUP($F36,'Project Summary'!$B$9:$M$106,7,FALSE),"") -> 2080 | K36: 2080 | L36: =IFERROR(J36-K36,"") -> 0
A37: 33 | B37: =HYPERLINK("Z:\MePork\000 綜合\020 報價合約\Quotation\2024\MS_Q1241_24_kp (C9644-24C Extension of Fitness Room at KBD Recreation & Sports Centre)\P1 - Payment\Payment records\"&A37&".PDF",A37) -> 33 | C37: 45852 | D37: INV14/7/2025 | F37: O-006 | G37: =IFERROR(VLOOKUP($F37,'Project Summary'!$B$9:$M$106,3,FALSE),"") -> FIRE EXTINGUISHER SAFETY CONSULTANT | H37: =IFERROR(VLOOKUP($F37,'Project Summary'!$B$9:$M$106,4,FALSE),"") -> 滅火筒安全顧問 | I37: =IFERROR(VLOOKUP($F37,'Project Summary'!$B$9:$M$106,5,FALSE),"") -> Safety | J37: =IFERROR(VLOOKUP($F37,'Project Summary'!$B$9:$M$106,7,FALSE),"") -> 272000 | K37: 16000 | L37: =IFERROR(J37-K37,"") -> 256000
A38: 34 | B38: =HYPERLINK("Z:\MePork\000 綜合\020 報價合約\Quotation\2024\MS_Q1241_24_kp (C9644-24C Extension of Fitness Room at KBD Recreation & Sports Centre)\P1 - Payment\Payment records\"&A38&".PDF",A38) -> 34 | C38: 45855 | D38: 12025082 | F38: SC-004A | G38: =IFERROR(VLOOKUP($F38,'Project Summary'!$B$9:$M$106,3,FALSE),"") -> YING PAK ENGINEERING COMPANY | H38: =IFERROR(VLOOKUP($F38,'Project Summary'!$B$9:$M$106,4,FALSE),"") -> 盈泊工程公司 | I38: MVAC Installation - IP-02 (VO) | J38: =IFERROR(VLOOKUP($F38,'Project Summary'!$B$9:$M$106,7,FALSE),"") -> 83000 | K38: 83000 | L38: =IFERROR(J38-K38,"") -> 0
A39: 35 | B39: =HYPERLINK("Z:\MePork\000 綜合\020 報價合約\Quotation\2024\MS_Q1241_24_kp (C9644-24C Extension of Fitness Room at KBD Recreation & Sports Centre)\P1 - Payment\Payment records\"&A39&".PDF",A39) -> 35 | C39: 45826 | D39: IVA01106-25 | F39: M-015 | G39: =IFERROR(VLOOKUP($F39,'Project Summary'!$B$9:$M$106,3,FALSE),"") -> ALCO LIGHTING (H.K.) LTD | H39: =IFERROR(VLOOKUP($F39,'Project Summary'!$B$9:$M$106,4,FALSE),"") -> 0 | I39: =IFERROR(VLOOKUP($F39,'Project Summary'!$B$9:$M$106,5,FALSE),"") -> Light fitting | J39: =IFERROR(VLOOKUP($F39,'Project Summary'!$B$9:$M$106,7,FALSE),"") -> 174600 | K39: 174600 | L39: =IFERROR(J39-K39,"") -> 0
A40: 36 | B40: =HYPERLINK("Z:\MePork\000 綜合\020 報價合約\Quotation\2024\MS_Q1241_24_kp (C9644-24C Extension of Fitness Room at KBD Recreation & Sports Centre)\P1 - Payment\Payment records\"&A40&".PDF",A40) -> 36 | C40: 45854 | D40: 12025064 | F40: SC-004 | G40: =IFERROR(VLOOKUP($F40,'Project Summary'!$B$9:$M$106,3,FALSE),"") -> YING PAK ENGINEERING COMPANY | H40: =IFERROR(VLOOKUP($F40,'Project Summary'!$B$9:$M$106,4,FALSE),"") -> 盈泊工程公司 | I40: MVAC Installation - IP-03 | J40: =IFERROR(VLOOKUP($F40,'Project Summary'!$B$9:$M$106,7,FALSE),"") -> 800000 | K40: 138000 | L40: =IFERROR(J40-K40,"") -> 662000
A41: 37 | B41: =HYPERLINK("Z:\MePork\000 綜合\020 報價合約\Quotation\2024\MS_Q1241_24_kp (C9644-24C Extension of Fitness Room at KBD Recreation & Sports Centre)\P1 - Payment\Payment records\"&A41&".PDF",A41) -> 37 | C41: 45862 | D41: 705330028 | F41: O-005 | G41: =IFERROR(VLOOKUP($F41,'Project Summary'!$B$9:$M$106,3,FALSE),"") -> Environmental Protection Department | H41: =IFERROR(VLOOKUP($F41,'Project Summary'!$B$9:$M$106,4,FALSE),"") -> 環境保護署 | I41: =IFERROR(VLOOKUP($F41,'Project Summary'!$B$9:$M$106,5,FALSE),"") -> Waste Dispoal | J41: =IFERROR(VLOOKUP($F41,'Project Summary'!$B$9:$M$106,7,FALSE),"") -> 27242.5 | K41: 4562.5 | L41: =IFERROR(J41-K41,"") -> 22680
A42: 38 | B42: =HYPERLINK("Z:\MePork\000 綜合\020 報價合約\Quotation\2024\MS_Q1241_24_kp (C9644-24C Extension of Fitness Room at KBD Recreation & Sports Centre)\P1 - Payment\Payment records\"&A42&".PDF",A42) -> 38 | C42: 45818 | D42: 64555 | F42: M-011.6 | G42: =IFERROR(VLOOKUP($F42,'Project Summary'!$B$9:$M$106,3,FALSE),"") -> SHUN SHING ELECTRICALS CO. LTD | H42: =IFERROR(VLOOKUP($F42,'Project Summary'!$B$9:$M$106,4,FALSE),"") -> 信成電器材料有限公司 | I42: =IFERROR(VLOOKUP($F42,'Project Summary'!$B$9:$M$106,5,FALSE),"") -> EL - Material | J42: =IFERROR(VLOOKUP($F42,'Project Summary'!$B$9:$M$106,7,FALSE),"") -> 5400 | K42: 5400 | L42: =IFERROR(J42-K42,"") -> 0
A43: 39 | B43: =HYPERLINK("Z:\MePork\000 綜合\020 報價合約\Quotation\2024\MS_Q1241_24_kp (C9644-24C Extension of Fitness Room at KBD Recreation & Sports Centre)\P1 - Payment\Payment records\"&A43&".PDF",A43) -> 39 | C43: 45798 | D43: 64426 | F43: M-011.8 | G43: =IFERROR(VLOOKUP($F43,'Project Summary'!$B$9:$M$106,3,FALSE),"") -> SHUN SHING ELECTRICALS CO. LTD | H43: =IFERROR(VLOOKUP($F43,'Project Summary'!$B$9:$M$106,4,FALSE),"") -> 信成電器材料有限公司 | I43: =IFERROR(VLOOKUP($F43,'Project Summary'!$B$9:$M$106,5,FALSE),"") -> EL - Material | J43: =IFERROR(VLOOKUP($F43,'Project Summary'!$B$9:$M$106,7,FALSE),"") -> 1988.3 | K43: 1988.3 | L43: =IFERROR(J43-K43,"") -> 0
A44: 40 | B44: =HYPERLINK("Z:\MePork\000 綜合\020 報價合約\Quotation\2024\MS_Q1241_24_kp (C9644-24C Extension of Fitness Room at KBD Recreation & Sports Centre)\P1 - Payment\Payment records\"&A44&".PDF",A44) -> 40 | C44: 45798 | D44: 64425 | F44: M-011.7 | G44: =IFERROR(VLOOKUP($F44,'Project Summary'!$B$9:$M$106,3,FALSE),"") -> SHUN SHING ELECTRICALS CO. LTD | H44: =IFERROR(VLOOKUP($F44,'Project Summary'!$B$9:$M$106,4,FALSE),"") -> 信成電器材料有限公司 | I44: =IFERROR(VLOOKUP($F44,'Project Summary'!$B$9:$M$106,5,FALSE),"") -> EL - Material | J44: =IFERROR(VLOOKUP($F44,'Project Summary'!$B$9:$M$106,7,FALSE),"") -> 1353 | K44: 1353 | L44: =IFERROR(J44-K44,"") -> 0
A45: 41 | B45: =HYPERLINK("Z:\MePork\000 綜合\020 報價合約\Quotation\2024\MS_Q1241_24_kp (C9644-24C Extension of Fitness Room at KBD Recreation & Sports Centre)\P1 - Payment\Payment records\"&A45&".PDF",A45) -> 41 | F45: SC-008.1 | G45: =IFERROR(VLOOKUP($F45,'Project Summary'!$B$9:$M$106,3,FALSE),"") -> WAH MAN ENGINEERING COMPANY | H45: =IFERROR(VLOOKUP($F45,'Project Summary'!$B$9:$M$106,4,FALSE),"") -> 華文工程有限公司 | I45: =IFERROR(VLOOKUP($F45,'Project Summary'!$B$9:$M$106,5,FALSE),"") -> Structural Engineering Consultancy | J45: =IFERROR(VLOOKUP($F45,'Project Summary'!$B$9:$M$106,7,FALSE),"") -> 6000 | K45: 6000 | L45: =IFERROR(J45-K45,"") -> 0
A46: 42 | B46: =HYPERLINK("Z:\MePork\000 綜合\020 報價合約\Quotation\2024\MS_Q1241_24_kp (C9644-24C Extension of Fitness Room at KBD Recreation & Sports Centre)\P1 - Payment\Payment records\"&A46&".PDF",A46) -> 42 | C46: 45867 | D46: DN2507000481 | F46: O-009 | G46: =IFERROR(VLOOKUP($F46,'Project Summary'!$B$9:$M$106,3,FALSE),"") -> UCMG | H46: =IFERROR(VLOOKUP($F46,'Project Summary'!$B$9:$M$106,4,FALSE),"") -> 聯康醫療 | I46: =IFERROR(VLOOKUP($F46,'Project Summary'!$B$9:$M$106,5,FALSE),"") -> Body Check | J46: =IFERROR(VLOOKUP($F46,'Project Summary'!$B$9:$M$106,7,FALSE),"") -> 1640 | K46: 270 | L46: =IFERROR(J46-K46,"") -> 1370 | P46: 扣宏發
A47: 43 | B47: =HYPERLINK("Z:\MePork\000 綜合\020 報價合約\Quotation\2024\MS_Q1241_24_kp (C9644-24C Extension of Fitness Room at KBD Recreation & Sports Centre)\P1 - Payment\Payment records\"&A47&".PDF",A47) -> 43 | C47: 45874 | D47: Q-CEL-FS-2411-01 | F47: SC-002 | G47: =IFERROR(VLOOKUP($F47,'Project Summary'!$B$9:$M$106,3,FALSE),"") -> CHASE ENGINEERING LIMITED | H47: =IFERROR(VLOOKUP($F47,'Project Summary'!$B$9:$M$106,4,FALSE),"") -> 大同工程有限公司 | I47: =IFERROR(VLOOKUP($F47,'Project Summary'!$B$9:$M$106,5,FALSE),"") -> Fire Services Installation | J47: =IFERROR(VLOOKUP($F47,'Project Summary'!$B$9:$M$106,7,FALSE),"") -> 800000 | K47: 116250 | L47: =IFERROR(J47-K47,"") -> 683750
A48: 44 | B48: =HYPERLINK("Z:\MePork\000 綜合\020 報價合約\Quotation\2024\MS_Q1241_24_kp (C9644-24C Extension of Fitness Room at KBD Recreation & Sports Centre)\P1 - Payment\Payment records\"&A48&".PDF",A48) -> 44 | C48: 45839 | D48: P24-28 | F48: SC-010 | G48: =IFERROR(VLOOKUP($F48,'Project Summary'!$B$9:$M$106,3,FALSE),"") -> CHIU MING COMPANY LIMITED | H48: =IFERROR(VLOOKUP($F48,'Project Summary'!$B$9:$M$106,4,FALSE),"") -> 照明工程有限公司 | I48: EL - IP-03 | J48: =IFERROR(VLOOKUP($F48,'Project Summary'!$B$9:$M$106,7,FALSE),"") -> 1100000 | K48: 54597.3 | L48: =IFERROR(J48-K48,"") -> 1045402.7
A49: 45 | B49: =HYPERLINK("Z:\MePork\000 綜合\020 報價合約\Quotation\2024\MS_Q1241_24_kp (C9644-24C Extension of Fitness Room at KBD Recreation & Sports Centre)\P1 - Payment\Payment records\"&A49&".PDF",A49) -> 45 | F49: O-013 | G49: =IFERROR(VLOOKUP($F49,'Project Summary'!$B$9:$M$106,3,FALSE),"") -> Miscellaneous | H49: =IFERROR(VLOOKUP($F49,'Project Summary'!$B$9:$M$106,4,FALSE),"") -> 0 | I49: =IFERROR(VLOOKUP($F49,'Project Summary'!$B$9:$M$106,5,FALSE),"") -> 0 | J49: =IFERROR(VLOOKUP($F49,'Project Summary'!$B$9:$M$106,7,FALSE),"") -> 12038.9 | K49: 6146.9 | L49: =IFERROR(J49-K49,"") -> 5892
A50: 46 | B50: =HYPERLINK("Z:\MePork\000 綜合\020 報價合約\Quotation\2024\MS_Q1241_24_kp (C9644-24C Extension of Fitness Room at KBD Recreation & Sports Centre)\P1 - Payment\Payment records\"&A50&".PDF",A50) -> 46 | C50: 45867 | D50: DN2507000479 | F50: O-009 | G50: =IFERROR(VLOOKUP($F50,'Project Summary'!$B$9:$M$106,3,FALSE),"") -> UCMG | H50: =IFERROR(VLOOKUP($F50,'Project Summary'!$B$9:$M$106,4,FALSE),"") -> 聯康醫療 | I50: =IFERROR(VLOOKUP($F50,'Project Summary'!$B$9:$M$106,5,FALSE),"") -> Body Check | J50: =IFERROR(VLOOKUP($F50,'Project Summary'!$B$9:$M$106,7,FALSE),"") -> 1640 | K50: 280 | L50: =IFERROR(J50-K50,"") -> 1360 | P50: 扣盈泊
A51: 47 | B51: =HYPERLINK("Z:\MePork\000 綜合\020 報價合約\Quotation\2024\MS_Q1241_24_kp (C9644-24C Extension of Fitness Room at KBD Recreation & Sports Centre)\P1 - Payment\Payment records\"&A51&".PDF",A51) -> 47 | C51: 45888 | D51: INV-WF-20250519 | F51: SC-003A | G51: =IFERROR(VLOOKUP($F51,'Project Summary'!$B$9:$M$106,3,FALSE),"") -> WANG FAT CONSTRUCTION CO. | H51: =IFERROR(VLOOKUP($F51,'Project Summary'!$B$9:$M$106,4,FALSE),"") -> 宏發建築工程公司 | I51: =IFERROR(VLOOKUP($F51,'Project Summary'!$B$9:$M$106,5,FALSE),"") -> Q167/21 搭架比EMSD驗收燈柱 | J51: =IFERROR(VLOOKUP($F51,'Project Summary'!$B$9:$M$106,7,FALSE),"") -> 15000 | K51: 15000 | L51: =IFERROR(J51-K51,"") -> 0
A52: 48 | B52: =HYPERLINK("Z:\MePork\000 綜合\020 報價合約\Quotation\2024\MS_Q1241_24_kp (C9644-24C Extension of Fitness Room at KBD Recreation & Sports Centre)\P1 - Payment\Payment records\"&A52&".PDF",A52) -> 48 | C52: 45882 | D52: 12025088 | F52: SC-004 | G52: =IFERROR(VLOOKUP($F52,'Project Summary'!$B$9:$M$106,3,FALSE),"") -> YING PAK ENGINEERING COMPANY | H52: =IFERROR(VLOOKUP($F52,'Project Summary'!$B$9:$M$106,4,FALSE),"") -> 盈泊工程公司 | I52: MVAC Installation - IP-04 | J52: =IFERROR(VLOOKUP($F52,'Project Summary'!$B$9:$M$106,7,FALSE),"") -> 800000 | K52: 108000 | L52: =IFERROR(J52-K52,"") -> 692000
A53: 49 | B53: =HYPERLINK("Z:\MePork\000 綜合\020 報價合約\Quotation\2024\MS_Q1241_24_kp (C9644-24C Extension of Fitness Room at KBD Recreation & Sports Centre)\P1 - Payment\Payment records\"&A53&".PDF",A53) -> 49 | C53: 45817 | D53: 3022374 | F53: O-013 | G53: =IFERROR(VLOOKUP($F53,'Project Summary'!$B$9:$M$106,3,FALSE),"") -> Miscellaneous | H53: =IFERROR(VLOOKUP($F53,'Project Summary'!$B$9:$M$106,4,FALSE),"") -> 0 | I53: =IFERROR(VLOOKUP($F53,'Project Summary'!$B$9:$M$106,5,FALSE),"") -> 0 | J53: =IFERROR(VLOOKUP($F53,'Project Summary'!$B$9:$M$106,7,FALSE),"") -> 12038.9 | K53: 460 | L53: =IFERROR(J53-K53,"") -> 11578.9
A54: 50 | B54: =HYPERLINK("Z:\MePork\000 綜合\020 報價合約\Quotation\2024\MS_Q1241_24_kp (C9644-24C Extension of Fitness Room at KBD Recreation & Sports Centre)\P1 - Payment\Payment records\"&A54&".PDF",A54) -> 50 | C54: 45882 | D54: INV13/8/2025 | F54: O-006 | G54: =IFERROR(VLOOKUP($F54,'Project Summary'!$B$9:$M$106,3,FALSE),"") -> FIRE EXTINGUISHER SAFETY CONSULTANT | H54: =IFERROR(VLOOKUP($F54,'Project Summary'!$B$9:$M$106,4,FALSE),"") -> 滅火筒安全顧問 | I54: =IFERROR(VLOOKUP($F54,'Project Summary'!$B$9:$M$106,5,FALSE),"") -> Safety | J54: =IFERROR(VLOOKUP($F54,'Project Summary'!$B$9:$M$106,7,FALSE),"") -> 272000 | K54: 16000 | L54: =IFERROR(J54-K54,"") -> 256000
A55: 50A | B55: =HYPERLINK("Z:\MePork\000 綜合\020 報價合約\Quotation\2024\MS_Q1241_24_kp (C9644-24C Extension of Fitness Room at KBD Recreation & Sports Centre)\P1 - Payment\Payment records\"&A55&".PDF",A55) -> 50A | C55: 45853 | D55: 250713 | F55: O-017 | G55: =IFERROR(VLOOKUP($F55,'Project Summary'!$B$9:$M$106,3,FALSE),"") -> Firewood Engineering Ltd. | H55: =IFERROR(VLOOKUP($F55,'Project Summary'!$B$9:$M$106,4,FALSE),"") -> 積富工程有限公司 | I55: =IFERROR(VLOOKUP($F55,'Project Summary'!$B$9:$M$106,5,FALSE),"") -> CP(NT)/Fire Marshal | J55: =IFERROR(VLOOKUP($F55,'Project Summary'!$B$9:$M$106,7,FALSE),"") -> 1500 | K55: 1500 | L55: =IFERROR(J55-K55,"") -> 0 | P55: 扣宏發
A56: 51 | B56: =HYPERLINK("Z:\MePork\000 綜合\020 報價合約\Quotation\2024\MS_Q1241_24_kp (C9644-24C Extension of Fitness Room at KBD Recreation & Sports Centre)\P1 - Payment\Payment records\"&A56&".PDF",A56) -> 51 | C56: 45902 | D56: 12025105 | F56: SC-004 | G56: =IFERROR(VLOOKUP($F56,'Project Summary'!$B$9:$M$106,3,FALSE),"") -> YING PAK ENGINEERING COMPANY | H56: =IFERROR(VLOOKUP($F56,'Project Summary'!$B$9:$M$106,4,FALSE),"") -> 盈泊工程公司 | I56: MVAC Installation - IP-05 | J56: =IFERROR(VLOOKUP($F56,'Project Summary'!$B$9:$M$106,7,FALSE),"") -> 800000 | K56: 80000 | L56: =L52-K56 -> 612000
A57: 52 | B57: =HYPERLINK("Z:\MePork\000 綜合\020 報價合約\Quotation\2024\MS_Q1241_24_kp (C9644-24C Extension of Fitness Room at KBD Recreation & Sports Centre)\P1 - Payment\Payment records\"&A57&".PDF",A57) -> 52 | C57: 9/9/205 | D57: P24-28 | F57: SC-010 | G57: =IFERROR(VLOOKUP($F57,'Project Summary'!$B$9:$M$106,3,FALSE),"") -> CHIU MING COMPANY LIMITED | H57: =IFERROR(VLOOKUP($F57,'Project Summary'!$B$9:$M$106,4,FALSE),"") -> 照明工程有限公司 | I57: EL - IP-04 | J57: =IFERROR(VLOOKUP($F57,'Project Summary'!$B$9:$M$106,7,FALSE),"") -> 1100000 | K57: 158545.5 | L57: =IFERROR(J57-K57,"") -> 941454.5
A58: 53 | B58: =HYPERLINK("Z:\MePork\000 綜合\020 報價合約\Quotation\2024\MS_Q1241_24_kp (C9644-24C Extension of Fitness Room at KBD Recreation & Sports Centre)\P1 - Payment\Payment records\"&A58&".PDF",A58) -> 53 | C58: 45856 | D58: 64769 | F58: M-011.15 | G58: =IFERROR(VLOOKUP($F58,'Project Summary'!$B$9:$M$106,3,FALSE),"") -> SHUN SHING ELECTRICALS CO. LTD | H58: =IFERROR(VLOOKUP($F58,'Project Summary'!$B$9:$M$106,4,FALSE),"") -> 信成電器材料有限公司 | I58: =IFERROR(VLOOKUP($F58,'Project Summary'!$B$9:$M$106,5,FALSE),"") -> EL - Material | J58: =IFERROR(VLOOKUP($F58,'Project Summary'!$B$9:$M$106,7,FALSE),"") -> 8909 | K58: 8909 | L58: =IFERROR(J58-K58,"") -> 0
A59: 54 | B59: =HYPERLINK("Z:\MePork\000 綜合\020 報價合約\Quotation\2024\MS_Q1241_24_kp (C9644-24C Extension of Fitness Room at KBD Recreation & Sports Centre)\P1 - Payment\Payment records\"&A59&".PDF",A59) -> 54 | C59: 45856 | D59: 64768 | F59: M-011.14 | G59: =IFERROR(VLOOKUP($F59,'Project Summary'!$B$9:$M$106,3,FALSE),"") -> SHUN SHING ELECTRICALS CO. LTD | H59: =IFERROR(VLOOKUP($F59,'Project Summary'!$B$9:$M$106,4,FALSE),"") -> 信成電器材料有限公司 | I59: =IFERROR(VLOOKUP($F59,'Project Summary'!$B$9:$M$106,5,FALSE),"") -> EL - Material | J59: =IFERROR(VLOOKUP($F59,'Project Summary'!$B$9:$M$106,7,FALSE),"") -> 6410 | K59: 6410 | L59: =IFERROR(J59-K59,"") -> 0
A60: 55 | B60: =HYPERLINK("Z:\MePork\000 綜合\020 報價合約\Quotation\2024\MS_Q1241_24_kp (C9644-24C Extension of Fitness Room at KBD Recreation & Sports Centre)\P1 - Payment\Payment records\"&A60&".PDF",A60) -> 55 | C60: 45903 | D60: 705330028 | F60: O-005 | G60: =IFERROR(VLOOKUP($F60,'Project Summary'!$B$9:$M$106,3,FALSE),"") -> Environmental Protection Department | H60: =IFERROR(VLOOKUP($F60,'Project Summary'!$B$9:$M$106,4,FALSE),"") -> 環境保護署 | I60: =IFERROR(VLOOKUP($F60,'Project Summary'!$B$9:$M$106,5,FALSE),"") -> Waste Dispoal | J60: =IFERROR(VLOOKUP($F60,'Project Summary'!$B$9:$M$106,7,FALSE),"") -> 27242.5 | K60: 540 | L60: =IFERROR(J60-K60,"") -> 26702.5
A61: 56 | B61: =HYPERLINK("Z:\MePork\000 綜合\020 報價合約\Quotation\2024\MS_Q1241_24_kp (C9644-24C Extension of Fitness Room at KBD Recreation & Sports Centre)\P1 - Payment\Payment records\"&A61&".PDF",A61) -> 56 | C61: 45870 | D61: 64864 | F61: M-011.10 | G61: =IFERROR(VLOOKUP($F61,'Project Summary'!$B$9:$M$106,3,FALSE),"") -> SHUN SHING ELECTRICALS CO. LTD | H61: =IFERROR(VLOOKUP($F61,'Project Summary'!$B$9:$M$106,4,FALSE),"") -> 信成電器材料有限公司 | I61: =IFERROR(VLOOKUP($F61,'Project Summary'!$B$9:$M$106,5,FALSE),"") -> EL - Material | J61: =IFERROR(VLOOKUP($F61,'Project Summary'!$B$9:$M$106,7,FALSE),"") -> 15497.2 | K61: 15497.2 | L61: =IFERROR(J61-K61,"") -> -1.8189894e-12
A62: 57 | B62: =HYPERLINK("Z:\MePork\000 綜合\020 報價合約\Quotation\2024\MS_Q1241_24_kp (C9644-24C Extension of Fitness Room at KBD Recreation & Sports Centre)\P1 - Payment\Payment records\"&A62&".PDF",A62) -> 57 | C62: 45868 | D62: 64846 | F62: M-011.13 | G62: =IFERROR(VLOOKUP($F62,'Project Summary'!$B$9:$M$106,3,FALSE),"") -> SHUN SHING ELECTRICALS CO. LTD | H62: =IFERROR(VLOOKUP($F62,'Project Summary'!$B$9:$M$106,4,FALSE),"") -> 信成電器材料有限公司 | I62: =IFERROR(VLOOKUP($F62,'Project Summary'!$B$9:$M$106,5,FALSE),"") -> EL - Material | J62: =IFERROR(VLOOKUP($F62,'Project Summary'!$B$9:$M$106,7,FALSE),"") -> 900 | K62: 900 | L62: =IFERROR(J62-K62,"") -> 0
A63: 58 | B63: =HYPERLINK("Z:\MePork\000 綜合\020 報價合約\Quotation\2024\MS_Q1241_24_kp (C9644-24C Extension of Fitness Room at KBD Recreation & Sports Centre)\P1 - Payment\Payment records\"&A63&".PDF",A63) -> 58 | C63: 45873 | D63: 64884 | F63: M-011.12 | G63: =IFERROR(VLOOKUP($F63,'Project Summary'!$B$9:$M$106,3,FALSE),"") -> SHUN SHING ELECTRICALS CO. LTD | H63: =IFERROR(VLOOKUP($F63,'Project Summary'!$B$9:$M$106,4,FALSE),"") -> 信成電器材料有限公司 | I63: =IFERROR(VLOOKUP($F63,'Project Summary'!$B$9:$M$106,5,FALSE),"") -> EL - Material | J63: =IFERROR(VLOOKUP($F63,'Project Summary'!$B$9:$M$106,7,FALSE),"") -> 6120 | K63: 6120 | L63: =IFERROR(J63-K63,"") -> 0
A64: 59 | B64: =HYPERLINK("Z:\MePork\000 綜合\020 報價合約\Quotation\2024\MS_Q1241_24_kp (C9644-24C Extension of Fitness Room at KBD Recreation & Sports Centre)\P1 - Payment\Payment records\"&A64&".PDF",A64) -> 59 | C64: 45856 | D64: 64767 | F64: M-011.11 | G64: =IFERROR(VLOOKUP($F64,'Project Summary'!$B$9:$M$106,3,FALSE),"") -> SHUN SHING ELECTRICALS CO. LTD | H64: =IFERROR(VLOOKUP($F64,'Project Summary'!$B$9:$M$106,4,FALSE),"") -> 信成電器材料有限公司 | I64: =IFERROR(VLOOKUP($F64,'Project Summary'!$B$9:$M$106,5,FALSE),"") -> EL - Material | J64: =IFERROR(VLOOKUP($F64,'Project Summary'!$B$9:$M$106,7,FALSE),"") -> 7200 | K64: 7200 | L64: =IFERROR(J64-K64,"") -> 0
A65: 60 | B65: =HYPERLINK("Z:\MePork\000 綜合\020 報價合約\Quotation\2024\MS_Q1241_24_kp (C9644-24C Extension of Fitness Room at KBD Recreation & Sports Centre)\P1 - Payment\Payment records\"&A65&".PDF",A65) -> 60 | C65: 45863 | D65: 64827 | F65: M-011.9 | G65: =IFERROR(VLOOKUP($F65,'Project Summary'!$B$9:$M$106,3,FALSE),"") -> SHUN SHING ELECTRICALS CO. LTD | H65: =IFERROR(VLOOKUP($F65,'Project Summary'!$B$9:$M$106,4,FALSE),"") -> 信成電器材料有限公司 | I65: =IFERROR(VLOOKUP($F65,'Project Summary'!$B$9:$M$106,5,FALSE),"") -> EL - Material | J65: =IFERROR(VLOOKUP($F65,'Project Summary'!$B$9:$M$106,7,FALSE),"") -> 2393.6 | K65: 2393.6 | L65: =IFERROR(J65-K65,"") -> 0
A66: 61 | B66: =HYPERLINK("Z:\MePork\000 綜合\020 報價合約\Quotation\2024\MS_Q1241_24_kp (C9644-24C Extension of Fitness Room at KBD Recreation & Sports Centre)\P1 - Payment\Payment records\"&A66&".PDF",A66) -> 61 | C66: 45901 | D66: P24-28 | F66: SC-010 | G66: =IFERROR(VLOOKUP($F66,'Project Summary'!$B$9:$M$106,3,FALSE),"") -> CHIU MING COMPANY LIMITED | H66: =IFERROR(VLOOKUP($F66,'Project Summary'!$B$9:$M$106,4,FALSE),"") -> 照明工程有限公司 | I66: EL - IP-05 | J66: =IFERROR(VLOOKUP($F66,'Project Summary'!$B$9:$M$106,7,FALSE),"") -> 1100000 | K66: 157554.65 | L66: =IFERROR(J66-K66,"") -> 942445.35
A67: 62 | B67: =HYPERLINK("Z:\MePork\000 綜合\020 報價合約\Quotation\2024\MS_Q1241_24_kp (C9644-24C Extension of Fitness Room at KBD Recreation & Sports Centre)\P1 - Payment\Payment records\"&A67&".PDF",A67) -> 62 | C67: 45916 | D67: INV16/9/2025 | F67: O-006 | G67: =IFERROR(VLOOKUP($F67,'Project Summary'!$B$9:$M$106,3,FALSE),"") -> FIRE EXTINGUISHER SAFETY CONSULTANT | H67: =IFERROR(VLOOKUP($F67,'Project Summary'!$B$9:$M$106,4,FALSE),"") -> 滅火筒安全顧問 | I67: =IFERROR(VLOOKUP($F67,'Project Summary'!$B$9:$M$106,5,FALSE),"") -> Safety | J67: =IFERROR(VLOOKUP($F67,'Project Summary'!$B$9:$M$106,7,FALSE),"") -> 272000 | K67: 16000 | L67: =IFERROR(J67-K67,"") -> 256000
A68: 63 | B68: =HYPERLINK("Z:\MePork\000 綜合\020 報價合約\Quotation\2024\MS_Q1241_24_kp (C9644-24C Extension of Fitness Room at KBD Recreation & Sports Centre)\P1 - Payment\Payment records\"&A68&".PDF",A68) -> 63 | C68: 45929 | D68: DN3400538 | F68: O-012 | G68: =IFERROR(VLOOKUP($F68,'Project Summary'!$B$9:$M$106,3,FALSE),"") -> CONSTRUCTION INDUSTRY COUNCIL | H68: =IFERROR(VLOOKUP($F68,'Project Summary'!$B$9:$M$106,4,FALSE),"") -> 建造業議會 | I68: =IFERROR(VLOOKUP($F68,'Project Summary'!$B$9:$M$106,5,FALSE),"") -> Levies | J68: =IFERROR(VLOOKUP($F68,'Project Summary'!$B$9:$M$106,7,FALSE),"") -> 14006 | K68: 5229 | L68: =IFERROR(J68-K68,"") -> 8777
A69: 64 | B69: =HYPERLINK("Z:\MePork\000 綜合\020 報價合約\Quotation\2024\MS_Q1241_24_kp (C9644-24C Extension of Fitness Room at KBD Recreation & Sports Centre)\P1 - Payment\Payment records\"&A69&".PDF",A69) -> 64 | C69: 45936 | D69: DN3648839 | F69: O-014 | G69: =IFERROR(VLOOKUP($F69,'Project Summary'!$B$9:$M$106,3,FALSE),"") -> PNEUMOCONIOSIS COMPENSATION FUND BOARD | H69: =IFERROR(VLOOKUP($F69,'Project Summary'!$B$9:$M$106,4,FALSE),"") -> 肺塵埃沉着病補償基金委員會 | I69: =IFERROR(VLOOKUP($F69,'Project Summary'!$B$9:$M$106,5,FALSE),"") -> Levies | J69: =IFERROR(VLOOKUP($F69,'Project Summary'!$B$9:$M$106,7,FALSE),"") -> 6279 | K69: 1480 | L69: =IFERROR(J69-K69,"") -> 4799
A70: 65 | B70: =HYPERLINK("Z:\MePork\000 綜合\020 報價合約\Quotation\2024\MS_Q1241_24_kp (C9644-24C Extension of Fitness Room at KBD Recreation & Sports Centre)\P1 - Payment\Payment records\"&A70&".PDF",A70) -> 65 | F70: SC-003 | G70: =IFERROR(VLOOKUP($F70,'Project Summary'!$B$9:$M$106,3,FALSE),"") -> WANG FAT CONSTRUCTION CO. | H70: =IFERROR(VLOOKUP($F70,'Project Summary'!$B$9:$M$106,4,FALSE),"") -> 宏發建築工程公司 | I70: =IFERROR(VLOOKUP($F70,'Project Summary'!$B$9:$M$106,5,FALSE),"") -> Builder's Works | J70: =IFERROR(VLOOKUP($F70,'Project Summary'!$B$9:$M$106,7,FALSE),"") -> 1900000 | K70: 199500 | L70: =IFERROR(J70-K70,"") -> 1700500
A71: 66 | B71: =HYPERLINK("Z:\MePork\000 綜合\020 報價合約\Quotation\2024\MS_Q1241_24_kp (C9644-24C Extension of Fitness Room at KBD Recreation & Sports Centre)\P1 - Payment\Payment records\"&A71&".PDF",A71) -> 66 | C71: 45945 | D71: 705330028 | F71: O-005 | G71: =IFERROR(VLOOKUP($F71,'Project Summary'!$B$9:$M$106,3,FALSE),"") -> Environmental Protection Department | H71: =IFERROR(VLOOKUP($F71,'Project Summary'!$B$9:$M$106,4,FALSE),"") -> 環境保護署 | I71: =IFERROR(VLOOKUP($F71,'Project Summary'!$B$9:$M$106,5,FALSE),"") -> Waste Dispoal | J71: =IFERROR(VLOOKUP($F71,'Project Summary'!$B$9:$M$106,7,FALSE),"") -> 27242.5 | K71: 500 | L71: =IFERROR(J71-K71,"") -> 26742.5
A72: 67 | B72: =HYPERLINK("Z:\MePork\000 綜合\020 報價合約\Quotation\2024\MS_Q1241_24_kp (C9644-24C Extension of Fitness Room at KBD Recreation & Sports Centre)\P1 - Payment\Payment records\"&A72&".PDF",A72) -> 67 | C72: 45931 | D72: P24-28 | F72: SC-010 | G72: =IFERROR(VLOOKUP($F72,'Project Summary'!$B$9:$M$106,3,FALSE),"") -> CHIU MING COMPANY LIMITED | H72: =IFERROR(VLOOKUP($F72,'Project Summary'!$B$9:$M$106,4,FALSE),"") -> 照明工程有限公司 | I72: EL - IP-06 | J72: =IFERROR(VLOOKUP($F72,'Project Summary'!$B$9:$M$106,7,FALSE),"") -> 1100000 | K72: 56468 | L72: =IFERROR(J72-K72,"") -> 1043532
A73: 68 | B73: =HYPERLINK("Z:\MePork\000 綜合\020 報價合約\Quotation\2024\MS_Q1241_24_kp (C9644-24C Extension of Fitness Room at KBD Recreation & Sports Centre)\P1 - Payment\Payment records\"&A73&".PDF",A73) -> 68 | C73: 45950 | D73: INV20/10/2025 | F73: O-006 | G73: =IFERROR(VLOOKUP($F73,'Project Summary'!$B$9:$M$106,3,FALSE),"") -> FIRE EXTINGUISHER SAFETY CONSULTANT | H73: =IFERROR(VLOOKUP($F73,'Project Summary'!$B$9:$M$106,4,FALSE),"") -> 滅火筒安全顧問 | I73: =IFERROR(VLOOKUP($F73,'Project Summary'!$B$9:$M$106,5,FALSE),"") -> Safety | J73: =IFERROR(VLOOKUP($F73,'Project Summary'!$B$9:$M$106,7,FALSE),"") -> 272000 | K73: 16000 | L73: =IFERROR(J73-K73,"") -> 256000
A74: 69 | B74: =HYPERLINK("Z:\MePork\000 綜合\020 報價合約\Quotation\2024\MS_Q1241_24_kp (C9644-24C Extension of Fitness Room at KBD Recreation & Sports Centre)\P1 - Payment\Payment records\"&A74&".PDF",A74) -> 69 | C74: 45939 | D74: 12025121 | F74: SC-004 | G74: =IFERROR(VLOOKUP($F74,'Project Summary'!$B$9:$M$106,3,FALSE),"") -> YING PAK ENGINEERING COMPANY | H74: =IFERROR(VLOOKUP($F74,'Project Summary'!$B$9:$M$106,4,FALSE),"") -> 盈泊工程公司 | I74: MVAC Installation - IP-06 | J74: =IFERROR(VLOOKUP($F74,'Project Summary'!$B$9:$M$106,7,FALSE),"") -> 800000 | K74: 80000 | L74: =IFERROR(J74-K74,"") -> 720000
A75: 70 | B75: =HYPERLINK("Z:\MePork\000 綜合\020 報價合約\Quotation\2024\MS_Q1241_24_kp (C9644-24C Extension of Fitness Room at KBD Recreation & Sports Centre)\P1 - Payment\Payment records\"&A75&".PDF",A75) -> 70 | C75: 45962 | D75: P24-28 | F75: SC-010 | G75: =IFERROR(VLOOKUP($F75,'Project Summary'!$B$9:$M$106,3,FALSE),"") -> CHIU MING COMPANY LIMITED | H75: =IFERROR(VLOOKUP($F75,'Project Summary'!$B$9:$M$106,4,FALSE),"") -> 照明工程有限公司 | I75: EL - IP-07 | J75: =IFERROR(VLOOKUP($F75,'Project Summary'!$B$9:$M$106,7,FALSE),"") -> 1100000 | K75: 14250 | L75: =IFERROR(J75-K75,"") -> 1085750
A76: 71 | B76: =HYPERLINK("Z:\MePork\000 綜合\020 報價合約\Quotation\2024\MS_Q1241_24_kp (C9644-24C Extension of Fitness Room at KBD Recreation & Sports Centre)\P1 - Payment\Payment records\"&A76&".PDF",A76) -> 71 | C76: 45967 | D76: 12025132 | F76: SC-004 | G76: =IFERROR(VLOOKUP($F76,'Project Summary'!$B$9:$M$106,3,FALSE),"") -> YING PAK ENGINEERING COMPANY | H76: =IFERROR(VLOOKUP($F76,'Project Summary'!$B$9:$M$106,4,FALSE),"") -> 盈泊工程公司 | I76: MVAC Installation - IP-07 | J76: =IFERROR(VLOOKUP($F76,'Project Summary'!$B$9:$M$106,7,FALSE),"") -> 800000 | K76: 80000 | L76: =IFERROR(J76-K76,"") -> 720000
A77: 72 | B77: =HYPERLINK("Z:\MePork\000 綜合\020 報價合約\Quotation\2024\MS_Q1241_24_kp (C9644-24C Extension of Fitness Room at KBD Recreation & Sports Centre)\P1 - Payment\Payment records\"&A77&".PDF",A77) -> 72 | C77: 45925 | D77: 65240 | F77: M-011.19 | G77: =IFERROR(VLOOKUP($F77,'Project Summary'!$B$9:$M$106,3,FALSE),"") -> SHUN SHING ELECTRICALS CO. LTD | H77: =IFERROR(VLOOKUP($F77,'Project Summary'!$B$9:$M$106,4,FALSE),"") -> 信成電器材料有限公司 | I77: =IFERROR(VLOOKUP($F77,'Project Summary'!$B$9:$M$106,5,FALSE),"") -> EL - Material | J77: =IFERROR(VLOOKUP($F77,'Project Summary'!$B$9:$M$106,7,FALSE),"") -> 4363 | K77: 4363 | L77: =IFERROR(J77-K77,"") -> 0
A78: 73 | B78: =HYPERLINK("Z:\MePork\000 綜合\020 報價合約\Quotation\2024\MS_Q1241_24_kp (C9644-24C Extension of Fitness Room at KBD Recreation & Sports Centre)\P1 - Payment\Payment records\"&A78&".PDF",A78) -> 73 | C78: 45909 | D78: 65083 | F78: M-011.17 | G78: =IFERROR(VLOOKUP($F78,'Project Summary'!$B$9:$M$106,3,FALSE),"") -> SHUN SHING ELECTRICALS CO. LTD | H78: =IFERROR(VLOOKUP($F78,'Project Summary'!$B$9:$M$106,4,FALSE),"") -> 信成電器材料有限公司 | I78: =IFERROR(VLOOKUP($F78,'Project Summary'!$B$9:$M$106,5,FALSE),"") -> EL - Material | J78: =IFERROR(VLOOKUP($F78,'Project Summary'!$B$9:$M$106,7,FALSE),"") -> 1803 | K78: 1803 | L78: =IFERROR(J78-K78,"") -> 0
A79: 74 | B79: =HYPERLINK("Z:\MePork\000 綜合\020 報價合約\Quotation\2024\MS_Q1241_24_kp (C9644-24C Extension of Fitness Room at KBD Recreation & Sports Centre)\P1 - Payment\Payment records\"&A79&".PDF",A79) -> 74 | C79: 45979 | D79: 65077 | F79: M-011.16 | G79: =IFERROR(VLOOKUP($F79,'Project Summary'!$B$9:$M$106,3,FALSE),"") -> SHUN SHING ELECTRICALS CO. LTD | H79: =IFERROR(VLOOKUP($F79,'Project Summary'!$B$9:$M$106,4,FALSE),"") -> 信成電器材料有限公司 | I79: =IFERROR(VLOOKUP($F79,'Project Summary'!$B$9:$M$106,5,FALSE),"") -> EL - Material | J79: =IFERROR(VLOOKUP($F79,'Project Summary'!$B$9:$M$106,7,FALSE),"") -> 2584 | K79: 2584 | L79: =IFERROR(J79-K79,"") -> 0
A80: 75 | B80: =HYPERLINK("Z:\MePork\000 綜合\020 報價合約\Quotation\2024\MS_Q1241_24_kp (C9644-24C Extension of Fitness Room at KBD Recreation & Sports Centre)\P1 - Payment\Payment records\"&A80&".PDF",A80) -> 75 | C80: 45910 | D80: 65088 | F80: M-011.18 | G80: =IFERROR(VLOOKUP($F80,'Project Summary'!$B$9:$M$106,3,FALSE),"") -> SHUN SHING ELECTRICALS CO. LTD | H80: =IFERROR(VLOOKUP($F80,'Project Summary'!$B$9:$M$106,4,FALSE),"") -> 信成電器材料有限公司 | I80: =IFERROR(VLOOKUP($F80,'Project Summary'!$B$9:$M$106,5,FALSE),"") -> EL - Material | J80: =IFERROR(VLOOKUP($F80,'Project Summary'!$B$9:$M$106,7,FALSE),"") -> 6425 | K80: 6425 | L80: =IFERROR(J80-K80,"") -> 0
A81: 76 | B81: =HYPERLINK("Z:\MePork\000 綜合\020 報價合約\Quotation\2024\MS_Q1241_24_kp (C9644-24C Extension of Fitness Room at KBD Recreation & Sports Centre)\P1 - Payment\Payment records\"&A81&".PDF",A81) -> 76 | C81: 45979 | D81: INV18/11/2025 | F81: O-006 | G81: =IFERROR(VLOOKUP($F81,'Project Summary'!$B$9:$M$106,3,FALSE),"") -> FIRE EXTINGUISHER SAFETY CONSULTANT | H81: =IFERROR(VLOOKUP($F81,'Project Summary'!$B$9:$M$106,4,FALSE),"") -> 滅火筒安全顧問 | I81: =IFERROR(VLOOKUP($F81,'Project Summary'!$B$9:$M$106,5,FALSE),"") -> Safety | J81: =IFERROR(VLOOKUP($F81,'Project Summary'!$B$9:$M$106,7,FALSE),"") -> 272000 | K81: 16000 | L81: =IFERROR(J81-K81,"") -> 256000
A82: 77 | B82: =HYPERLINK("Z:\MePork\000 綜合\020 報價合約\Quotation\2024\MS_Q1241_24_kp (C9644-24C Extension of Fitness Room at KBD Recreation & Sports Centre)\P1 - Payment\Payment records\"&A82&".PDF",A82) -> 77 | C82: 45995 | F82: SC-003 | G82: =IFERROR(VLOOKUP($F82,'Project Summary'!$B$9:$M$106,3,FALSE),"") -> WANG FAT CONSTRUCTION CO. | H82: =IFERROR(VLOOKUP($F82,'Project Summary'!$B$9:$M$106,4,FALSE),"") -> 宏發建築工程公司 | I82: =IFERROR(VLOOKUP($F82,'Project Summary'!$B$9:$M$106,5,FALSE),"") -> Builder's Works | J82: =IFERROR(VLOOKUP($F82,'Project Summary'!$B$9:$M$106,7,FALSE),"") -> 1900000 | K82: 365750 | L82: =IFERROR(J82-K82,"") -> 1534250
A83: 78 | B83: =HYPERLINK("Z:\MePork\000 綜合\020 報價合約\Quotation\2024\MS_Q1241_24_kp (C9644-24C Extension of Fitness Room at KBD Recreation & Sports Centre)\P1 - Payment\Payment records\"&A83&".PDF",A83) -> 78 | C83: 45990 | D83: 12025137 | F83: SC-004 | G83: =IFERROR(VLOOKUP($F83,'Project Summary'!$B$9:$M$106,3,FALSE),"") -> YING PAK ENGINEERING COMPANY | H83: =IFERROR(VLOOKUP($F83,'Project Summary'!$B$9:$M$106,4,FALSE),"") -> 盈泊工程公司 | I83: MVAC Installation - IP-08 | J83: =IFERROR(VLOOKUP($F83,'Project Summary'!$B$9:$M$106,7,FALSE),"") -> 800000 | K83: 100000 | L83: =IFERROR(J83-K83,"") -> 700000
A84: 79 | B84: =HYPERLINK("Z:\MePork\000 綜合\020 報價合約\Quotation\2024\MS_Q1241_24_kp (C9644-24C Extension of Fitness Room at KBD Recreation & Sports Centre)\P1 - Payment\Payment records\"&A84&".PDF",A84) -> 79 | C84: 45967 | D84: Q-CEL-FS-2411-01-VO-01-R1 | F84: SC-002A | G84: =IFERROR(VLOOKUP($F84,'Project Summary'!$B$9:$M$106,3,FALSE),"") -> CHASE ENGINEERING LIMITED | H84: =IFERROR(VLOOKUP($F84,'Project Summary'!$B$9:$M$106,4,FALSE),"") -> 大同工程有限公司 | I84: =IFERROR(VLOOKUP($F84,'Project Summary'!$B$9:$M$106,5,FALSE),"") -> Supply Smoke Detector | J84: =IFERROR(VLOOKUP($F84,'Project Summary'!$B$9:$M$106,7,FALSE),"") -> 12000 | K84: 12000 | L84: =IFERROR(J84-K84,"") -> 0 | R84: 扣宏發
A85: 80 | B85: =HYPERLINK("Z:\MePork\000 綜合\020 報價合約\Quotation\2024\MS_Q1241_24_kp (C9644-24C Extension of Fitness Room at KBD Recreation & Sports Centre)\P1 - Payment\Payment records\"&A85&".PDF",A85) -> 80 | C85: 45992 | D85: P24-28 | F85: SC-010 | G85: =IFERROR(VLOOKUP($F85,'Project Summary'!$B$9:$M$106,3,FALSE),"") -> CHIU MING COMPANY LIMITED | H85: =IFERROR(VLOOKUP($F85,'Project Summary'!$B$9:$M$106,4,FALSE),"") -> 照明工程有限公司 | I85: EL - IP-08 | J85: =IFERROR(VLOOKUP($F85,'Project Summary'!$B$9:$M$106,7,FALSE),"") -> 1100000 | K85: 68537.75 | L85: =IFERROR(J85-K85,"") -> 1031462.2
A86: 81 | B86: =HYPERLINK("Z:\MePork\000 綜合\020 報價合約\Quotation\2024\MS_Q1241_24_kp (C9644-24C Extension of Fitness Room at KBD Recreation & Sports Centre)\P1 - Payment\Payment records\"&A86&".PDF",A86) -> 81 | C86: 46003 | F86: O-013 | G86: =IFERROR(VLOOKUP($F86,'Project Summary'!$B$9:$M$106,3,FALSE),"") -> Miscellaneous | H86: =IFERROR(VLOOKUP($F86,'Project Summary'!$B$9:$M$106,4,FALSE),"") -> 0 | I86: =IFERROR(VLOOKUP($F86,'Project Summary'!$B$9:$M$106,5,FALSE),"") -> 0 | J86: =IFERROR(VLOOKUP($F86,'Project Summary'!$B$9:$M$106,7,FALSE),"") -> 12038.9 | K86: 1827 | L86: =IFERROR(J86-K86,"") -> 10211.9
A87: 82 | B87: =HYPERLINK("Z:\MePork\000 綜合\020 報價合約\Quotation\2024\MS_Q1241_24_kp (C9644-24C Extension of Fitness Room at KBD Recreation & Sports Centre)\P1 - Payment\Payment records\"&A87&".PDF",A87) -> 82 | C87: 46010 | F87: O-013 | G87: =IFERROR(VLOOKUP($F87,'Project Summary'!$B$9:$M$106,3,FALSE),"") -> Miscellaneous | H87: =IFERROR(VLOOKUP($F87,'Project Summary'!$B$9:$M$106,4,FALSE),"") -> 0 | I87: =IFERROR(VLOOKUP($F87,'Project Summary'!$B$9:$M$106,5,FALSE),"") -> 0 | J87: =IFERROR(VLOOKUP($F87,'Project Summary'!$B$9:$M$106,7,FALSE),"") -> 12038.9 | K87: 1685 | L87: =IFERROR(J87-K87,"") -> 10353.9
A88: 83 | B88: =HYPERLINK("Z:\MePork\000 綜合\020 報價合約\Quotation\2024\MS_Q1241_24_kp (C9644-24C Extension of Fitness Room at KBD Recreation & Sports Centre)\P1 - Payment\Payment records\"&A88&".PDF",A88) -> 83 | C88: 46017 | D88: INV26/12/2025 | F88: O-006 | G88: =IFERROR(VLOOKUP($F88,'Project Summary'!$B$9:$M$106,3,FALSE),"") -> FIRE EXTINGUISHER SAFETY CONSULTANT | H88: =IFERROR(VLOOKUP($F88,'Project Summary'!$B$9:$M$106,4,FALSE),"") -> 滅火筒安全顧問 | I88: =IFERROR(VLOOKUP($F88,'Project Summary'!$B$9:$M$106,5,FALSE),"") -> Safety | J88: =IFERROR(VLOOKUP($F88,'Project Summary'!$B$9:$M$106,7,FALSE),"") -> 272000 | K88: 16000 | L88: =IFERROR(J88-K88,"") -> 256000
A89: 84 | B89: =HYPERLINK("Z:\MePork\000 綜合\020 報價合約\Quotation\2024\MS_Q1241_24_kp (C9644-24C Extension of Fitness Room at KBD Recreation & Sports Centre)\P1 - Payment\Payment records\"&A89&".PDF",A89) -> 84 | C89: 45992 | D89: P24-28 | F89: SC-010.1 | G89: =IFERROR(VLOOKUP($F89,'Project Summary'!$B$9:$M$106,3,FALSE),"") -> CHIU MING COMPANY LIMITED | H89: =IFERROR(VLOOKUP($F89,'Project Summary'!$B$9:$M$106,4,FALSE),"") -> 照明工程有限公司 | I89: EL - IP-09(VO-01 (EI-01)) | J89: =IFERROR(VLOOKUP($F89,'Project Summary'!$B$9:$M$106,7,FALSE),"") -> 112880 | K89: 56440 | L89: =IFERROR(J89-K89,"") -> 56440
A90: 85.1 | B90: 85.1 | C90: 46054 | D90: P24-28 | F90: SC-010 | G90: =IFERROR(VLOOKUP($F90,'Project Summary'!$B$9:$M$106,3,FALSE),"") -> CHIU MING COMPANY LIMITED | H90: =IFERROR(VLOOKUP($F90,'Project Summary'!$B$9:$M$106,4,FALSE),"") -> 照明工程有限公司 | I90: EL - IP-11 | J90: =IFERROR(VLOOKUP($F90,'Project Summary'!$B$9:$M$106,7,FALSE),"") -> 1100000 | K90: 45698.8 | L90: =IFERROR(J90-K90,"") -> 1054301.2
A91: 85 | B91: =HYPERLINK("Z:\MePork\000 綜合\020 報價合約\Quotation\2024\MS_Q1241_24_kp (C9644-24C Extension of Fitness Room at KBD Recreation & Sports Centre)\P1 - Payment\Payment records\"&A91&".PDF",A91) -> 85 | C91: 46054 | D91: P24-28 | F91: SC-002 | G91: =IFERROR(VLOOKUP($F91,'Project Summary'!$B$9:$M$106,3,FALSE),"") -> CHASE ENGINEERING LIMITED | H91: =IFERROR(VLOOKUP($F91,'Project Summary'!$B$9:$M$106,4,FALSE),"") -> 大同工程有限公司 | I91: =IFERROR(VLOOKUP($F91,'Project Summary'!$B$9:$M$106,5,FALSE),"") -> Fire Services Installation | J91: =IFERROR(VLOOKUP($F91,'Project Summary'!$B$9:$M$106,7,FALSE),"") -> 800000 | K91: 118750 | L91: =IFERROR(J91-K91,"") -> 681250
A92: 86 | B92: =HYPERLINK("Z:\MePork\000 綜合\020 報價合約\Quotation\2024\MS_Q1241_24_kp (C9644-24C Extension of Fitness Room at KBD Recreation & Sports Centre)\P1 - Payment\Payment records\"&A92&".PDF",A92) -> 86 | C92: 46042 | D92: DN3717931 | F92: O-014 | G92: =IFERROR(VLOOKUP($F92,'Project Summary'!$B$9:$M$106,3,FALSE),"") -> PNEUMOCONIOSIS COMPENSATION FUND BOARD | H92: =IFERROR(VLOOKUP($F92,'Project Summary'!$B$9:$M$106,4,FALSE),"") -> 肺塵埃沉着病補償基金委員會 | I92: =IFERROR(VLOOKUP($F92,'Project Summary'!$B$9:$M$106,5,FALSE),"") -> Levies | J92: =IFERROR(VLOOKUP($F92,'Project Summary'!$B$9:$M$106,7,FALSE),"") -> 6279 | K92: 1174 | L92: =IFERROR(J92-K92,"") -> 5105
A93: 87 | B93: =HYPERLINK("Z:\MePork\000 綜合\020 報價合約\Quotation\2024\MS_Q1241_24_kp (C9644-24C Extension of Fitness Room at KBD Recreation & Sports Centre)\P1 - Payment\Payment records\"&A93&".PDF",A93) -> 87 | C93: 46049 | D93: P24-28 | F93: SC-010 | G93: =IFERROR(VLOOKUP($F93,'Project Summary'!$B$9:$M$106,3,FALSE),"") -> CHIU MING COMPANY LIMITED | H93: =IFERROR(VLOOKUP($F93,'Project Summary'!$B$9:$M$106,4,FALSE),"") -> 照明工程有限公司 | I93: EL - IP-10 | J93: =IFERROR(VLOOKUP($F93,'Project Summary'!$B$9:$M$106,7,FALSE),"") -> 1100000 | K93: 38000 | L93: =IFERROR(J93-K93,"") -> 1062000
A94: 88 | B94: =HYPERLINK("Z:\MePork\000 綜合\020 報價合約\Quotation\2024\MS_Q1241_24_kp (C9644-24C Extension of Fitness Room at KBD Recreation & Sports Centre)\P1 - Payment\Payment records\"&A94&".PDF",A94) -> 88 | C94: 45964 | D94: 65300 | F94: M-011.20 | G94: SHUN SHING ELECTRICALS CO. LTD | H94: 信成電器材料有限公司 | I94: EL - Material | J94: =IFERROR(VLOOKUP($F94,'Project Summary'!$B$9:$M$106,7,FALSE),"") -> 475.4 | K94: 475.4 | L94: =IFERROR(J94-K94,"") -> 0
A95: 89 | B95: =HYPERLINK("Z:\MePork\000 綜合\020 報價合約\Quotation\2024\MS_Q1241_24_kp (C9644-24C Extension of Fitness Room at KBD Recreation & Sports Centre)\P1 - Payment\Payment records\"&A95&".PDF",A95) -> 89 | C95: 46086 | D95: 65758 | F95: M-011.22 | G95: SHUN SHING ELECTRICALS CO. LTD | H95: 信成電器材料有限公司 | I95: EL - Material | J95: =IFERROR(VLOOKUP($F95,'Project Summary'!$B$9:$M$106,7,FALSE),"") -> 275.2 | K95: 275.2 | L95: =IFERROR(J95-K95,"") -> 0
A96: 90 | B96: =HYPERLINK("Z:\MePork\000 綜合\020 報價合約\Quotation\2024\MS_Q1241_24_kp (C9644-24C Extension of Fitness Room at KBD Recreation & Sports Centre)\P1 - Payment\Payment records\"&A96&".PDF",A96) -> 90 | C96: 46032 | D96: 65581 | F96: M-011.25 | G96: SHUN SHING ELECTRICALS CO. LTD | H96: 信成電器材料有限公司 | I96: EL - Material | J96: =IFERROR(VLOOKUP($F96,'Project Summary'!$B$9:$M$106,7,FALSE),"") -> 8460 | K96: 8460 | L96: =IFERROR(J96-K96,"") -> 0
A97: 91 | B97: =HYPERLINK("Z:\MePork\000 綜合\020 報價合約\Quotation\2024\MS_Q1241_24_kp (C9644-24C Extension of Fitness Room at KBD Recreation & Sports Centre)\P1 - Payment\Payment records\"&A97&".PDF",A97) -> 91 | C97: 46041 | D97: 65617 | F97: M-011.24 | G97: SHUN SHING ELECTRICALS CO. LTD | H97: 信成電器材料有限公司 | I97: EL - Material | J97: =IFERROR(VLOOKUP($F97,'Project Summary'!$B$9:$M$106,7,FALSE),"") -> 1625 | K97: 1625 | L97: =IFERROR(J97-K97,"") -> 0
A98: 91.1 | B98: =HYPERLINK("Z:\MePork\000 綜合\020 報價合約\Quotation\2024\MS_Q1241_24_kp (C9644-24C Extension of Fitness Room at KBD Recreation & Sports Centre)\P1 - Payment\Payment records\"&A98&".PDF",A98) -> 91.1 | C98: 46032 | D98: 65579 | F98: M-011.23 | G98: SHUN SHING ELECTRICALS CO. LTD | H98: 信成電器材料有限公司 | I98: EL - Material | J98: =IFERROR(VLOOKUP($F98,'Project Summary'!$B$9:$M$106,7,FALSE),"") -> 6335 | K98: 6335 | L98: =IFERROR(J98-K98,"") -> 0
A99: 91.2 | B99: =HYPERLINK("Z:\MePork\000 綜合\020 報價合約\Quotation\2024\MS_Q1241_24_kp (C9644-24C Extension of Fitness Room at KBD Recreation & Sports Centre)\P1 - Payment\Payment records\"&A99&".PDF",A99) -> 91.2 | C99: 4/32/2026 | D99: 65750 | F99: M-011.21 | G99: SHUN SHING ELECTRICALS CO. LTD | H99: 信成電器材料有限公司 | I99: EL - Material | J99: =IFERROR(VLOOKUP($F99,'Project Summary'!$B$9:$M$106,7,FALSE),"") -> 16028.8 | K99: 16028.8 | L99: =IFERROR(J99-K99,"") -> 0
A100: 92 | B100: =HYPERLINK("Z:\MePork\000 綜合\020 報價合約\Quotation\2024\MS_Q1241_24_kp (C9644-24C Extension of Fitness Room at KBD Recreation & Sports Centre)\P1 - Payment\Payment records\"&A100&".PDF",A100) -> 92 | C100: 46059 | D100: 705330028 | F100: O-005 | G100: =IFERROR(VLOOKUP($F100,'Project Summary'!$B$9:$M$106,3,FALSE),"") -> Environmental Protection Department | H100: =IFERROR(VLOOKUP($F100,'Project Summary'!$B$9:$M$106,4,FALSE),"") -> 環境保護署 | I100: =IFERROR(VLOOKUP($F100,'Project Summary'!$B$9:$M$106,5,FALSE),"") -> Waste Dispoal | J100: =IFERROR(VLOOKUP($F100,'Project Summary'!$B$9:$M$106,7,FALSE),"") -> 27242.5 | K100: 2940 | L100: =IFERROR(J100-K100,"") -> 24302.5
...

Sheet Project Summary
A1: 美博工程服務有限公司
A2: MS_Q1241_24_kp (MTR C9644-24C Extension of Fitness Room at KBD Recreation & Sports Centre)
A4: 總承建商(MC): | B4: Mepork Engineering Services Limited | I4: 承建金額: | J4: =Summary!B18 -> 7400000
I5: (a) | L5: $1,720,000.00 Contingency
I6: (A) Sub-total: | J6: =SUM(J4:J4) -> 7400000
A8: Item | B8: Sub-contractors' No. | C8: Quotation Copy | D8: Sub-contractors' Name | E8: Company Name (in Chinese) | F8: Nature of S/C Works | G8: Contract Charge | H8: Contract Sum | I8: VO | J8: Revised Contract Sum | K8: Remark | L8: 合約會簽表 (10萬以上) | M8: Contract | N8: 定標會議紀錄 (100萬以上) | O8: 報價已簽名 | P8: 正本已存檔 | Q8: OA
A9: 1 | B9: O-001 | C9: =HYPERLINK("Z:\MePork\000 綜合\020 報價合約\Quotation\2024\MS_Q1241_24_kp (C9644-24C Extension of Fitness Room at KBD Recreation & Sports Centre)\P1 - Payment\Quotation Records\"&B9&".PDF",B9) -> O-001 | D9: REALIFE INSURANCE BROKERS LTD. | E9: 恒傑保險業務有限公司 | F9: Insurance - EC | H9: 44360 | J9: =H9+I9 -> 44360 | L9: - | M9: OK | N9: OK | P9: OK | Q9: 45640 | R9: =J9/Summary!B18 -> 0.0059945946
A10: 1A | B10: O-001.1 | C10: =HYPERLINK("Z:\MePork\000 綜合\020 報價合約\Quotation\2024\MS_Q1241_24_kp (C9644-24C Extension of Fitness Room at KBD Recreation & Sports Centre)\P1 - Payment\Quotation Records\"&B10&".PDF",B10) -> O-001.1 | D10: REALIFE INSURANCE BROKERS LTD. | E10: 恒傑保險業務有限公司 | F10: Insurance - EC Extension | H10: 12366.35 | J10: =H10+I10 -> 12366.35 | Q10: 46049
A11: 2 | B11: SC-002 | C11: =HYPERLINK("Z:\MePork\000 綜合\020 報價合約\Quotation\2024\MS_Q1241_24_kp (C9644-24C Extension of Fitness Room at KBD Recreation & Sports Centre)\P1 - Payment\Quotation Records\"&B11&".PDF",B11) -> SC-002 | D11: CHASE ENGINEERING LIMITED | E11: 大同工程有限公司 | F11: Fire Services Installation | H11: 800000 | J11: =H11+I11 -> 800000 | L11: OK | M11: OK | N11: - | O11: OK | P11: Quotation saved | Q11: 45647
A12: 2A | B12: SC-002A | C12: =HYPERLINK("Z:\MePork\000 綜合\020 報價合約\Quotation\2024\MS_Q1241_24_kp (C9644-24C Extension of Fitness Room at KBD Recreation & Sports Centre)\P1 - Payment\Quotation Records\"&B12&".PDF",B12) -> SC-002A | D12: CHASE ENGINEERING LIMITED | E12: 大同工程有限公司 | F12: Supply Smoke Detector | H12: 12000 | J12: =H12+I12 -> 12000 | K12: 扣宏發 | Q12: 45978
A13: 3 | B13: SC-003 | C13: =HYPERLINK("Z:\MePork\000 綜合\020 報價合約\Quotation\2024\MS_Q1241_24_kp (C9644-24C Extension of Fitness Room at KBD Recreation & Sports Centre)\P1 - Payment\Quotation Records\"&B13&".PDF",B13) -> SC-003 | D13: WANG FAT CONSTRUCTION CO. | E13: 宏發建築工程公司 | F13: Builder's Works | H13: 1900000 | J13: =H13+I13 -> 1900000 | L13: OK | M13: OK | O13: OK | P13: Quotation saved | Q13: 45647
A14: 3A | B14: SC-003A | C14: =HYPERLINK("Z:\MePork\000 綜合\020 報價合約\Quotation\2024\MS_Q1241_24_kp (C9644-24C Extension of Fitness Room at KBD Recreation & Sports Centre)\P1 - Payment\Quotation Records\"&B14&".PDF",B14) -> SC-003A | D14: WANG FAT CONSTRUCTION CO. | E14: 宏發建築工程公司 | F14: Q167/21 搭架比EMSD驗收燈柱 | H14: 15000 | J14: =H14+I14 -> 15000 | Q14: 45828
A15: 3B | B15: SC-003B | D15: WANG FAT CONSTRUCTION CO. | E15: 宏發建築工程公司 | F15: Tony 帳款 | H15: =350700+796500-500000 -> 647200 | J15: =H15+I15 -> 647200
A16: 4 | B16: SC-004 | C16: =HYPERLINK("Z:\MePork\000 綜合\020 報價合約\Quotation\2024\MS_Q1241_24_kp (C9644-24C Extension of Fitness Room at KBD Recreation & Sports Centre)\P1 - Payment\Quotation Records\"&B16&".PDF",B16) -> SC-004 | D16: YING PAK ENGINEERING COMPANY | E16: 盈泊工程公司 | F16: MVAC Installation | H16: 800000 | J16: =H16+I16 -> 800000 | L16: OK | M16: OK | N16: - | O16: OK | P16: Quotation saved | Q16: 45647
A17: 5A | B17: SC-004A | C17: =HYPERLINK("Z:\MePork\000 綜合\020 報價合約\Quotation\2024\MS_Q1241_24_kp (C9644-24C Extension of Fitness Room at KBD Recreation & Sports Centre)\P1 - Payment\Quotation Records\"&B17&".PDF",B17) -> SC-004A | D17: YING PAK ENGINEERING COMPANY | E17: 盈泊工程公司 | F17: 代買冷氣機 | H17: 83000 | J17: =H17+I17 -> 83000 | Q17: 45861
A18: 5 | B18: O-005 | C18: =HYPERLINK("Z:\MePork\000 綜合\020 報價合約\Quotation\2024\MS_Q1241_24_kp (C9644-24C Extension of Fitness Room at KBD Recreation & Sports Centre)\P1 - Payment\Quotation Records\"&B18&".PDF",B18) -> O-005 | D18: Environmental Protection Department | E18: 環境保護署 | F18: Waste Dispoal | H18: =15000+4562.5+540+500+2940+520+3180 -> 27242.5 | J18: =H18+I18 -> 27242.5 | K18: $15,000 Deposit | L18: - | M18: - | N18: - | O18: - | P18: - | Q18: -
A19: 6 | B19: O-006 | C19: =HYPERLINK("Z:\MePork\000 綜合\020 報價合約\Quotation\2024\MS_Q1241_24_kp (C9644-24C Extension of Fitness Room at KBD Recreation & Sports Centre)\P1 - Payment\Quotation Records\"&B19&".PDF",B19) -> O-006 | D19: FIRE EXTINGUISHER SAFETY CONSULTANT | E19: 滅火筒安全顧問 | F19: Safety | H19: =16000*17 -> 272000 | J19: =H19+I19 -> 272000 | K19: $16,000 / month | L19: OK | M19: - | N19: - | O19: OK | P19: OK | Q19: 45646
A20: 6.2 | B20: O-006.2 | C20: =HYPERLINK("Z:\MePork\000 綜合\020 報價合約\Quotation\2024\MS_Q1241_24_kp (C9644-24C Extension of Fitness Room at KBD Recreation & Sports Centre)\P1 - Payment\Quotation Records\"&B20&".PDF",B20) -> O-006.2 | D20: FIRE EXTINGUISHER SAFETY CONSULTANT | E20: 滅火筒安全顧問 | F20: Safety 延期 | H20: 112000 | J20: =H20+I20 -> 112000 | Q20: 46175
A21: 6.1 | B21: O-006.1 | C21: =HYPERLINK("Z:\MePork\000 綜合\020 報價合約\Quotation\2024\MS_Q1241_24_kp (C9644-24C Extension of Fitness Room at KBD Recreation & Sports Centre)\P1 - Payment\Quotation Records\"&B21&".PDF",B21) -> O-006.1 | D21: FIRE EXTINGUISHER SAFETY CONSULTANT | E21: 滅火筒安全顧問 | F21: Safety Review | H21: 12000 | J21: =H21+I21 -> 12000 | L21: - | M21: - | N21: - | O21: OK | P21: OK | Q21: 45775
A22: 7 | B22: O-007 | C22: =HYPERLINK("Z:\MePork\000 綜合\020 報價合約\Quotation\2024\MS_Q1241_24_kp (C9644-24C Extension of Fitness Room at KBD Recreation & Sports Centre)\P1 - Payment\Quotation Records\"&B22&".PDF",B22) -> O-007 | D22: MTR | F22: CP Training | H22: =500+1000+500 -> 2000 | J22: =H22+I22 -> 2000 | L22: - | M22: - | N22: - | O22: - | P22: - | Q22: -
A23: 8 | B23: SC-008 | C23: =HYPERLINK("Z:\MePork\000 綜合\020 報價合約\Quotation\2024\MS_Q1241_24_kp (C9644-24C Extension of Fitness Room at KBD Recreation & Sports Centre)\P1 - Payment\Quotation Records\"&B23&".PDF",B23) -> SC-008 | D23: WAH MAN ENGINEERING COMPANY | E23: 華文工程有限公司 | F23: Design of Hoarding | H23: 9500 | J23: =H23+I23 -> 9500
A24: 8.1 | B24: SC-008.1 | C24: =HYPERLINK("Z:\MePork\000 綜合\020 報價合約\Quotation\2024\MS_Q1241_24_kp (C9644-24C Extension of Fitness Room at KBD Recreation & Sports Centre)\P1 - Payment\Quotation Records\"&B24&".PDF",B24) -> SC-008.1 | D24: WAH MAN ENGINEERING COMPANY | E24: 華文工程有限公司 | F24: Structural Engineering Consultancy | H24: 6000 | J24: =H24+I24 -> 6000 | Q24: 45873
A25: 9 | B25: O-009 | C25: =HYPERLINK("Z:\MePork\000 綜合\020 報價合約\Quotation\2024\MS_Q1241_24_kp (C9644-24C Extension of Fitness Room at KBD Recreation & Sports Centre)\P1 - Payment\Quotation Records\"&B25&".PDF",B25) -> O-009 | D25: UCMG | E25: 聯康醫療 | F25: Body Check | H25: =270*2+270+280+270+280 -> 1640 | J25: =H25+I25 -> 1640
A26: 10 | B26: SC-010 | C26: =HYPERLINK("Z:\MePork\000 綜合\020 報價合約\Quotation\2024\MS_Q1241_24_kp (C9644-24C Extension of Fitness Room at KBD Recreation & Sports Centre)\P1 - Payment\Quotation Records\"&B26&".PDF",B26) -> SC-010 | D26: CHIU MING COMPANY LIMITED | E26: 照明工程有限公司 | F26: EL | H26: 1100000 | J26: =H26+I26 -> 1100000
A27: 10.1 | B27: SC-010.1 | C27: =HYPERLINK("Z:\MePork\000 綜合\020 報價合約\Quotation\2024\MS_Q1241_24_kp (C9644-24C Extension of Fitness Room at KBD Recreation & Sports Centre)\P1 - Payment\Quotation Records\"&B27&".PDF",B27) -> SC-010.1 | D27: CHIU MING COMPANY LIMITED | E27: 照明工程有限公司 | F27: EL - VO-01 (EI-01) | H27: 112880 | J27: =H27+I27 -> 112880 | Q27: 45669
A28: 11 | B28: M-011.1 | C28: =HYPERLINK("Z:\MePork\000 綜合\020 報價合約\Quotation\2024\MS_Q1241_24_kp (C9644-24C Extension of Fitness Room at KBD Recreation & Sports Centre)\P1 - Payment\Quotation Records\"&B28&".PDF",B28) -> M-011.1 | D28: SHUN SHING ELECTRICALS CO. LTD | E28: 信成電器材料有限公司 | F28: EL - Material | H28: =9*3660 -> 32940 | J28: =H28+I28 -> 32940 | Q28: 45861
A29: 11 | B29: M-011.2 | C29: =HYPERLINK("Z:\MePork\000 綜合\020 報價合約\Quotation\2024\MS_Q1241_24_kp (C9644-24C Extension of Fitness Room at KBD Recreation & Sports Centre)\P1 - Payment\Quotation Records\"&B29&".PDF",B29) -> M-011.2 | D29: SHUN SHING ELECTRICALS CO. LTD | E29: 信成電器材料有限公司 | F29: EL - Material | H29: =7*4440+7975 -> 39055 | J29: =H29+I29 -> 39055 | Q29: 45861
A30: 11 | B30: M-011.3 | C30: =HYPERLINK("Z:\MePork\000 綜合\020 報價合約\Quotation\2024\MS_Q1241_24_kp (C9644-24C Extension of Fitness Room at KBD Recreation & Sports Centre)\P1 - Payment\Quotation Records\"&B30&".PDF",B30) -> M-011.3 | D30: SHUN SHING ELECTRICALS CO. LTD | E30: 信成電器材料有限公司 | F30: EL - Material | H30: =6*3660 -> 21960 | J30: =H30+I30 -> 21960 | Q30: 45861
A31: 11 | B31: M-011.4 | C31: =HYPERLINK("Z:\MePork\000 綜合\020 報價合約\Quotation\2024\MS_Q1241_24_kp (C9644-24C Extension of Fitness Room at KBD Recreation & Sports Centre)\P1 - Payment\Quotation Records\"&B31&".PDF",B31) -> M-011.4 | D31: SHUN SHING ELECTRICALS CO. LTD | E31: 信成電器材料有限公司 | F31: EL - Material | H31: =7*2820 -> 19740 | J31: =H31+I31 -> 19740 | Q31: 45861
A32: 11 | B32: M-011.5 | C32: =HYPERLINK("Z:\MePork\000 綜合\020 報價合約\Quotation\2024\MS_Q1241_24_kp (C9644-24C Extension of Fitness Room at KBD Recreation & Sports Centre)\P1 - Payment\Quotation Records\"&B32&".PDF",B32) -> M-011.5 | D32: SHUN SHING ELECTRICALS CO. LTD | E32: 信成電器材料有限公司 | F32: EL - Material | H32: =2080 -> 2080 | J32: =H32+I32 -> 2080 | Q32: 45861
A33: 11 | B33: M-011.6 | C33: =HYPERLINK("Z:\MePork\000 綜合\020 報價合約\Quotation\2024\MS_Q1241_24_kp (C9644-24C Extension of Fitness Room at KBD Recreation & Sports Centre)\P1 - Payment\Quotation Records\"&B33&".PDF",B33) -> M-011.6 | D33: SHUN SHING ELECTRICALS CO. LTD | E33: 信成電器材料有限公司 | F33: EL - Material | H33: 5400 | J33: =H33+I33 -> 5400 | Q33: 45861
A34: 11 | B34: M-011.7 | C34: =HYPERLINK("Z:\MePork\000 綜合\020 報價合約\Quotation\2024\MS_Q1241_24_kp (C9644-24C Extension of Fitness Room at KBD Recreation & Sports Centre)\P1 - Payment\Quotation Records\"&B34&".PDF",B34) -> M-011.7 | D34: SHUN SHING ELECTRICALS CO. LTD | E34: 信成電器材料有限公司 | F34: EL - Material | H34: 1353 | J34: =H34+I34 -> 1353 | Q34: 45861
A35: 11 | B35: M-011.8 | C35: =HYPERLINK("Z:\MePork\000 綜合\020 報價合約\Quotation\2024\MS_Q1241_24_kp (C9644-24C Extension of Fitness Room at KBD Recreation & Sports Centre)\P1 - Payment\Quotation Records\"&B35&".PDF",B35) -> M-011.8 | D35: SHUN SHING ELECTRICALS CO. LTD | E35: 信成電器材料有限公司 | F35: EL - Material | H35: 1988.3 | J35: =H35+I35 -> 1988.3 | Q35: 45861
A36: 11 | B36: M-011.9 | C36: =HYPERLINK("Z:\MePork\000 綜合\020 報價合約\Quotation\2024\MS_Q1241_24_kp (C9644-24C Extension of Fitness Room at KBD Recreation & Sports Centre)\P1 - Payment\Quotation Records\"&B36&".PDF",B36) -> M-011.9 | D36: SHUN SHING ELECTRICALS CO. LTD | E36: 信成電器材料有限公司 | F36: EL - Material | H36: =16*115.1+20*14+50*4+2*36 -> 2393.6 | J36: =H36+I36 -> 2393.6 | Q36: 45861
A37: 11 | B37: M-011.10 | C37: =HYPERLINK("Z:\MePork\000 綜合\020 報價合約\Quotation\2024\MS_Q1241_24_kp (C9644-24C Extension of Fitness Room at KBD Recreation & Sports Centre)\P1 - Payment\Quotation Records\"&B37&".PDF",B37) -> M-011.10 | D37: SHUN SHING ELECTRICALS CO. LTD | E37: 信成電器材料有限公司 | F37: EL - Material | H37: =80*28+100*2.5+200+200+40*28+10*37+5*67+100*1.5+50*136.9+11*64.8+7*439.2 -> 15497.2 | J37: =H37+I37 -> 15497.2 | Q37: 45861
A38: 11 | B38: M-011.11 | C38: =HYPERLINK("Z:\MePork\000 綜合\020 報價合約\Quotation\2024\MS_Q1241_24_kp (C9644-24C Extension of Fitness Room at KBD Recreation & Sports Centre)\P1 - Payment\Quotation Records\"&B38&".PDF",B38) -> M-011.11 | D38: SHUN SHING ELECTRICALS CO. LTD | E38: 信成電器材料有限公司 | F38: EL - Material | H38: =80*28+20*36+200*2.5+200+200*1.5+50*1.5+50*1.5+50*3+30*3+50*28+2*375+100*7 -> 7200 | J38: =H38+I38 -> 7200 | Q38: 45861
A39: 11 | B39: M-011.12 | C39: =HYPERLINK("Z:\MePork\000 綜合\020 報價合約\Quotation\2024\MS_Q1241_24_kp (C9644-24C Extension of Fitness Room at KBD Recreation & Sports Centre)\P1 - Payment\Quotation Records\"&B39&".PDF",B39) -> M-011.12 | D39: SHUN SHING ELECTRICALS CO. LTD | E39: 信成電器材料有限公司 | F39: EL - Material | H39: =3*2040 -> 6120 | J39: =H39+I39 -> 6120 | Q39: 45861
A40: 11 | B40: M-011.13 | C40: =HYPERLINK("Z:\MePork\000 綜合\020 報價合約\Quotation\2024\MS_Q1241_24_kp (C9644-24C Extension of Fitness Room at KBD Recreation & Sports Centre)\P1 - Payment\Quotation Records\"&B40&".PDF",B40) -> M-011.13 | D40: SHUN SHING ELECTRICALS CO. LTD | E40: 信成電器材料有限公司 | F40: EL - Material | H40: 900 | J40: =H40+I40 -> 900 | Q40: 45861
A41: 11 | B41: M-011.14 | C41: =HYPERLINK("Z:\MePork\000 綜合\020 報價合約\Quotation\2024\MS_Q1241_24_kp (C9644-24C Extension of Fitness Room at KBD Recreation & Sports Centre)\P1 - Payment\Quotation Records\"&B41&".PDF",B41) -> M-011.14 | D41: SHUN SHING ELECTRICALS CO. LTD | E41: 信成電器材料有限公司 | F41: EL - Material | H41: =50*8+20*13+50*18+50*8+50*13+100*3.3+100*2+3*36+6*20+20*115.1+20*27+50*4 -> 6410 | J41: =H41+I41 -> 6410 | Q41: 45861
A42: 11 | B42: M-011.15 | C42: =HYPERLINK("Z:\MePork\000 綜合\020 報價合約\Quotation\2024\MS_Q1241_24_kp (C9644-24C Extension of Fitness Room at KBD Recreation & Sports Centre)\P1 - Payment\Quotation Records\"&B42&".PDF",B42) -> M-011.15 | D42: SHUN SHING ELECTRICALS CO. LTD | E42: 信成電器材料有限公司 | F42: EL - Material | H42: =60*136.9+480+85+2*15+20*3+10*4 -> 8909 | J42: =H42+I42 -> 8909 | Q42: 45861
A43: 11 | B43: M-011.16 | C43: =HYPERLINK("Z:\MePork\000 綜合\020 報價合約\Quotation\2024\MS_Q1241_24_kp (C9644-24C Extension of Fitness Room at KBD Recreation & Sports Centre)\P1 - Payment\Quotation Records\"&B43&".PDF",B43) -> M-011.16 | D43: SHUN SHING ELECTRICALS CO. LTD | E43: 信成電器材料有限公司 | F43: EL - Material | H43: =30*28+40*28+24+50*12 -> 2584 | J43: =H43+I43 -> 2584 | Q43: 45861
A44: 11 | B44: M-011.17 | C44: =HYPERLINK("Z:\MePork\000 綜合\020 報價合約\Quotation\2024\MS_Q1241_24_kp (C9644-24C Extension of Fitness Room at KBD Recreation & Sports Centre)\P1 - Payment\Quotation Records\"&B44&".PDF",B44) -> M-011.17 | D44: SHUN SHING ELECTRICALS CO. LTD | E44: 信成電器材料有限公司 | F44: EL - Material | H44: =30*36+50*1.5+50*3+100*3+25*0.6+25+100*0.68+30*3 -> 1803 | J44: =H44+I44 -> 1803 | Q44: 45861
A45: 11 | B45: M-011.18 | C45: =HYPERLINK("Z:\MePork\000 綜合\020 報價合約\Quotation\2024\MS_Q1241_24_kp (C9644-24C Extension of Fitness Room at KBD Recreation & Sports Centre)\P1 - Payment\Quotation Records\"&B45&".PDF",B45) -> M-011.18 | D45: SHUN SHING ELECTRICALS CO. LTD | E45: 信成電器材料有限公司 | F45: EL - Material | H45: =5*1200+50*4+50*1.5+50*3 -> 6425 | J45: =H45+I45 -> 6425 | Q45: 45861
A46: 11 | B46: M-011.19 | C46: =HYPERLINK("Z:\MePork\000 綜合\020 報價合約\Quotation\2024\MS_Q1241_24_kp (C9644-24C Extension of Fitness Room at KBD Recreation & Sports Centre)\P1 - Payment\Quotation Records\"&B46&".PDF",B46) -> M-011.19 | D46: SHUN SHING ELECTRICALS CO. LTD | E46: 信成電器材料有限公司 | F46: EL - Material | H46: =5*37+100+2*480+20*136.9+1000*0.38 -> 4363 | J46: =H46+I46 -> 4363 | Q46: 45861
A47: 11 | B47: M-011.20 | C47: =HYPERLINK("Z:\MePork\000 綜合\020 報價合約\Quotation\2024\MS_Q1241_24_kp (C9644-24C Extension of Fitness Room at KBD Recreation & Sports Centre)\P1 - Payment\Quotation Records\"&B47&".PDF",B47) -> M-011.20 | D47: SHUN SHING ELECTRICALS CO. LTD | E47: 信成電器材料有限公司 | F47: EL - Material | H47: =4*115.1+5*3 -> 475.4 | J47: =H47+I47 -> 475.4 | Q47: 46142
A48: 11 | B48: M-011.21 | C48: =HYPERLINK("Z:\MePork\000 綜合\020 報價合約\Quotation\2024\MS_Q1241_24_kp (C9644-24C Extension of Fitness Room at KBD Recreation & Sports Centre)\P1 - Payment\Quotation Records\"&B48&".PDF",B48) -> M-011.21 | D48: SHUN SHING ELECTRICALS CO. LTD | E48: 信成電器材料有限公司 | F48: EL - Material | H48: =40*28+100*2.5+15*153+100*6.3+7*219+10*308+8*411.8+292.8+3*179.2+20*145.9+3*26 -> 16028.8 | J48: =H48+I48 -> 16028.8 | Q48: 46142
A49: 11 | B49: M-011.22 | C49: =HYPERLINK("Z:\MePork\000 綜合\020 報價合約\Quotation\2024\MS_Q1241_24_kp (C9644-24C Extension of Fitness Room at KBD Recreation & Sports Centre)\P1 - Payment\Quotation Records\"&B49&".PDF",B49) -> M-011.22 | D49: SHUN SHING ELECTRICALS CO. LTD | E49: 信成電器材料有限公司 | F49: EL - Material | H49: =2*115.1+30*1.5 -> 275.2 | J49: =H49+I49 -> 275.2 | Q49: 46142
A50: 11 | B50: M-011.23 | C50: =HYPERLINK("Z:\MePork\000 綜合\020 報價合約\Quotation\2024\MS_Q1241_24_kp (C9644-24C Extension of Fitness Room at KBD Recreation & Sports Centre)\P1 - Payment\Quotation Records\"&B50&".PDF",B50) -> M-011.23 | D50: SHUN SHING ELECTRICALS CO. LTD | E50: 信成電器材料有限公司 | F50: EL - Material | H50: =60*28+150*2.5+300+200+100*1.5+300*1.5+100*3+20*20.5+50*28+50*8+10*13+30*18 -> 6335 | J50: =H50+I50 -> 6335 | Q50: 46142
A51: 11 | B51: M-011.24 | C51: =HYPERLINK("Z:\MePork\000 綜合\020 報價合約\Quotation\2024\MS_Q1241_24_kp (C9644-24C Extension of Fitness Room at KBD Recreation & Sports Centre)\P1 - Payment\Quotation Records\"&B51&".PDF",B51) -> M-011.24 | D51: SHUN SHING ELECTRICALS CO. LTD | E51: 信成電器材料有限公司 | F51: EL - Material | H51: 1625 | J51: =H51+I51 -> 1625 | Q51: 46142
A52: 11 | B52: M-011.25 | C52: =HYPERLINK("Z:\MePork\000 綜合\020 報價合約\Quotation\2024\MS_Q1241_24_kp (C9644-24C Extension of Fitness Room at KBD Recreation & Sports Centre)\P1 - Payment\Quotation Records\"&B52&".PDF",B52) -> M-011.25 | D52: SHUN SHING ELECTRICALS CO. LTD | E52: 信成電器材料有限公司 | F52: EL - Material | H52: =100*2+50*153+480+85+3*15 -> 8460 | J52: =H52+I52 -> 8460 | Q52: 46142
A53: 11 | B53: M-011.26 | C53: =HYPERLINK("Z:\MePork\000 綜合\020 報價合約\Quotation\2024\MS_Q1241_24_kp (C9644-24C Extension of Fitness Room at KBD Recreation & Sports Centre)\P1 - Payment\Quotation Records\"&B53&".PDF",B53) -> M-011.26 | D53: SHUN SHING ELECTRICALS CO. LTD | E53: 信成電器材料有限公司 | F53: EL - Material | H53: =5*26+2*390+700+50*3+20*115.1+50*8+50*24+5*14+20*38+300*1.2+10*58+400 -> 7832 | J53: =H53+I53 -> 7832 | Q53: 46174
A54: 11 | B54: M-011.27 | C54: =HYPERLINK("Z:\MePork\000 綜合\020 報價合約\Quotation\2024\MS_Q1241_24_kp (C9644-24C Extension of Fitness Room at KBD Recreation & Sports Centre)\P1 - Payment\Quotation Records\"&B54&".PDF",B54) -> M-011.27 | J54: =H54+I54 -> 0
A55: 11 | B55: M-011.28 | C55: =HYPERLINK("Z:\MePork\000 綜合\020 報價合約\Quotation\2024\MS_Q1241_24_kp (C9644-24C Extension of Fitness Room at KBD Recreation & Sports Centre)\P1 - Payment\Quotation Records\"&B55&".PDF",B55) -> M-011.28 | J55: =H55+I55 -> 0
A56: 11 | B56: M-011.29 | C56: =HYPERLINK("Z:\MePork\000 綜合\020 報價合約\Quotation\2024\MS_Q1241_24_kp (C9644-24C Extension of Fitness Room at KBD Recreation & Sports Centre)\P1 - Payment\Quotation Records\"&B56&".PDF",B56) -> M-011.29 | J56: =H56+I56 -> 0
A57: 11 | B57: M-011.30 | C57: =HYPERLINK("Z:\MePork\000 綜合\020 報價合約\Quotation\2024\MS_Q1241_24_kp (C9644-24C Extension of Fitness Room at KBD Recreation & Sports Centre)\P1 - Payment\Quotation Records\"&B57&".PDF",B57) -> M-011.30 | J57: =H57+I57 -> 0
A58: 11 | B58: M-011.31 | C58: =HYPERLINK("Z:\MePork\000 綜合\020 報價合約\Quotation\2024\MS_Q1241_24_kp (C9644-24C Extension of Fitness Room at KBD Recreation & Sports Centre)\P1 - Payment\Quotation Records\"&B58&".PDF",B58) -> M-011.31 | J58: =H58+I58 -> 0
A59: 12 | B59: O-012 | C59: =HYPERLINK("Z:\MePork\000 綜合\020 報價合約\Quotation\2024\MS_Q1241_24_kp (C9644-24C Extension of Fitness Room at KBD Recreation & Sports Centre)\P1 - Payment\Quotation Records\"&B59&".PDF",B59) -> O-012 | D59: CONSTRUCTION INDUSTRY COUNCIL | E59: 建造業議會 | F59: Levies | H59: =1493+5229+7284 -> 14006 | J59: =H59+I59 -> 14006
A60: 13 | B60: O-013 | C60: =HYPERLINK("Z:\MePork\000 綜合\020 報價合約\Quotation\2024\MS_Q1241_24_kp (C9644-24C Extension of Fitness Room at KBD Recreation & Sports Centre)\P1 - Payment\Quotation Records\"&B60&".PDF",B60) -> O-013 | D60: Miscellaneous | H60: =6146.9+1920+460+1827+1685 -> 12038.9 | J60: =H60+I60 -> 12038.9
A61: 14 | B61: O-014 | C61: =HYPERLINK("Z:\MePork\000 綜合\020 報價合約\Quotation\2024\MS_Q1241_24_kp (C9644-24C Extension of Fitness Room at KBD Recreation & Sports Centre)\P1 - Payment\Quotation Records\"&B61&".PDF",B61) -> O-014 | D61: PNEUMOCONIOSIS COMPENSATION FUND BOARD | E61: 肺塵埃沉着病補償基金委員會 | F61: Levies | H61: =422+1480+1174+3203 -> 6279 | J61: =H61+I61 -> 6279
A62: 15 | B62: M-015 | C62: =HYPERLINK("Z:\MePork\000 綜合\020 報價合約\Quotation\2024\MS_Q1241_24_kp (C9644-24C Extension of Fitness Room at KBD Recreation & Sports Centre)\P1 - Payment\Quotation Records\"&B62&".PDF",B62) -> M-015 | D62: ALCO LIGHTING (H.K.) LTD | F62: Light fitting | H62: 174600 | J62: =H62+I62 -> 174600 | Q62: 45861
A63: 15 | B63: M-015.1 | C63: =HYPERLINK("Z:\MePork\000 綜合\020 報價合約\Quotation\2024\MS_Q1241_24_kp (C9644-24C Extension of Fitness Room at KBD Recreation & Sports Centre)\P1 - Payment\Quotation Records\"&B63&".PDF",B63) -> M-015.1 | D63: ALCO LIGHTING (H.K.) LTD | F63: Light fitting | H63: 32220 | J63: =H63+I63 -> 32220 | Q63: 46127
A64: 16 | B64: O-016 | C64: =HYPERLINK("Z:\MePork\000 綜合\020 報價合約\Quotation\2024\MS_Q1241_24_kp (C9644-24C Extension of Fitness Room at KBD Recreation & Sports Centre)\P1 - Payment\Quotation Records\"&B64&".PDF",B64) -> O-016 | D64: UCEM | E64: 聯康醫療 | J64: =H64+I64 -> 0
A65: 17 | B65: O-017 | C65: =HYPERLINK("Z:\MePork\000 綜合\020 報價合約\Quotation\2024\MS_Q1241_24_kp (C9644-24C Extension of Fitness Room at KBD Recreation & Sports Centre)\P1 - Payment\Quotation Records\"&B65&".PDF",B65) -> O-017 | D65: Firewood Engineering Ltd. | E65: 積富工程有限公司 | F65: CP(NT)/Fire Marshal | G65: * | H65: 1500 | J65: =H65+I65 -> 1500 | K65: $1,500/CP(NT) $1,450/Fire Marshal 扣判頭 | Q65: 45880
A66: 18 | B66: O-018 | C66: =HYPERLINK("Z:\MePork\000 綜合\020 報價合約\Quotation\2024\MS_Q1241_24_kp (C9644-24C Extension of Fitness Room at KBD Recreation & Sports Centre)\P1 - Payment\Quotation Records\"&B66&".PDF",B66) -> O-018 | D66: South China Inspection & Testing Ltd. | E66: 華南檢測有限公司 | F66: Testing | H66: 3280 | J66: =H66+I66 -> 3280 | Q66: 46174
A67: 18.1 | B67: O-018.1 | D67: South China Inspection & Testing Ltd. | E67: 華南檢測有限公司 | F67: 由宏發建築工程公司代付 | H67: 43640 | J67: =H67+I67 -> 43640 | Q67: 46177
A68: 19 | B68: SC-019 | C68: =HYPERLINK("Z:\MePork\000 綜合\020 報價合約\Quotation\2024\MS_Q1241_24_kp (C9644-24C Extension of Fitness Room at KBD Recreation & Sports Centre)\P1 - Payment\Quotation Records\"&B68&".PDF",B68) -> SC-019 | D68: CHING YAN ENGINEERING COMPANY LIMITED | E68: 晴昕工程有限公司 | F68: 復康會 No. 752 To Q1241 | H68: 95000 | J68: =H68+I68 -> 95000 | Q68: 46178
A69: 20 | B69: SC-020 | C69: =HYPERLINK("Z:\MePork\000 綜合\020 報價合約\Quotation\2024\MS_Q1241_24_kp (C9644-24C Extension of Fitness Room at KBD Recreation & Sports Centre)\P1 - Payment\Quotation Records\"&B69&".PDF",B69) -> SC-020 | D69: Brilliant Lighting Limited | E69: 恒亮照明有限公司 | F69: LED Exit Sign,由Dennis Chan 代付 | H69: 277 | J69: =H69+I69 -> 277 | Q69: 46178
A70: 21 | B70: SC-021 | C70: =HYPERLINK("Z:\MePork\000 綜合\020 報價合約\Quotation\2024\MS_Q1241_24_kp (C9644-24C Extension of Fitness Room at KBD Recreation & Sports Centre)\P1 - Payment\Quotation Records\"&B70&".PDF",B70) -> SC-021 | J70: =H70+I70 -> 0
A71: 22 | B71: SC-022 | C71: =HYPERLINK("Z:\MePork\000 綜合\020 報價合約\Quotation\2024\MS_Q1241_24_kp (C9644-24C Extension of Fitness Room at KBD Recreation & Sports Centre)\P1 - Payment\Quotation Records\"&B71&".PDF",B71) -> SC-022 | J71: =H71+I71 -> 0
A72: 23 | B72: SC-023 | C72: =HYPERLINK("Z:\MePork\000 綜合\020 報價合約\Quotation\2024\MS_Q1241_24_kp (C9644-24C Extension of Fitness Room at KBD Recreation & Sports Centre)\P1 - Payment\Quotation Records\"&B72&".PDF",B72) -> SC-023 | J72: =H72+I72 -> 0
I73: (B) Sub-total : | J73: =SUM(J9:J72) -> 6580182.2
I74: (C)Excluded Contract Charge item : | J74: =SUMIF(G41:G72,K74,J41:J72)*-1 -> -1500 | K74: *
B75: M-0XX | C75: Material | I75: 財務會作調撥(人工分攤) | J75: 1362556.4
B76: SC-0XX | C76: Sub-Contractor | I76: (D) = (B)+(C): | J76: =SUM(J73:J75) -> 7941238.7
B77: O-0XX | C77: Other | I77: (E) = (A)-(D)預計利潤: | J77: =J6-J76 -> -541238.65 | K77: (原預計利潤率6.7%)
I78: 預計利潤率: | J78: =J77/J6 -> -0.073140358
